{"-L7dgkBePJFdPLhhyfzc":0,"-L7dgkftsVrbrWyFE1sJ":0,"-L7dglA9G5xNH6c5xTo4":0,"-L7dglePHP6CE4ioBuCx":0,"-L7dgm8dSfoNzK2KtqpH":0,"-L7dgmcuL0Ho7nIVjYhk":0,"-L7dgn78QhNdpksYV76O":0,"-L7dgnbPgyjlHfiwd5A8":0,"-L7dgo5d1W2qoLYwPnc4":0,"-L7dgo_tSb8EEjC7MPoE":0,"-L7dgp48udQMs7Rtq4xl":0,"-L7dgpZOyefmyvOxFBpC":0,"-L7dgq2d9vur5nG7BKNs":0,"-L7dgqXsZTDlSqvBHUmE":0,"-L7dgr18mydGYZtOaERA":0,"-L7dgrWOZItNYsXTWMxs":0,"-L7dgs-dtT04ZIvqAgG_":0,"-L7dgsUs0XVwajgGWnfh":0,"-L7dgsz7RHGnqlka93Bm":0,"-L7dgtTN9QmJOewV47Zi":0,"-L7dgtxczk1tO9UEcpq8":0,"-L7dguRtgsiGuZW51eOk":0,"-L7dguw8Yj5IlCGSWoIC":0,"-L7dgvQOxwnhxrbOeju5":0,"-L7dgvuc--_aAs3T9N4o":0,"-L7dgwOt3CUf1aTSpZE8":0,"-L7dgwt8KTxc-5zLaQ4F":0,"-L7dgxNN31jgyZrICwJM":0,"-L7dgxrcqwSAj8cjfWAF":0,"-L7dgyLsOFLb-A1cqrcK":0,"-L7dgyq7rfUpwTl_Wz4i":0,"-L7dgzKNkZmiq8HPn2Xs":0,"-L7dgzocc5ptvw4tfbY_":0,"-L7dh-IsfQ-_mt5l2bTd":0,"-L7dh-n7gvnAUekOYYet":0,"-L7dh0HM0B7MOaHPBd3S":0,"-L7dh0lbMiSVrFv-C_MP":0,"-L7dh1FsldonLi4HuGHk":0,"-L7dh1k7JQWhJnwswLyW":0,"-L7dh2ENRRedfnN9q6gl":0,"-L7dh2ibcXUCMo26QEDg":0,"-L7dh3Crp1S99yGRSl3K":0,"-L7dh3h7WiEne9CuT0DU":0,"-L7dh4BMFcDJqM0qtJBm":0,"-L7dh4fbo9ytW_HjPbzg":0,"-L7dh59r58ZDl_PlXNfy":0,"-L7dh5e6wCtqdNb2G-pB":0,"-L7dh68MJ2ZAjSZsd8mU":0,"-L7dh6cb8uZqn-kLYZ4q":0,"-L7dh76rb0Yi5wb36Vru":0,"-L7dh7b6PGy3-rkq2nTv":0,"-L7dh85MMB8wpIWDp6pf":0,"-L7dh8_bgRFnl9dHgkOJ":0,"-L7dh93rZLPu4kARXx19":0,"-L7dh9Z6pMjZEL_Tg9hu":0,"-L7dhA2MTemCnHSNZyU9":0,"-L7dhAXbm_eBCDOfUwCU":0,"-L7dhB0sM6yQ6Lljq0Cb":0,"-L7dhBW6NKuHeCHfsMBE":0,"-L7dhC-LYkJ5UuYeF6j1":0,"-L7dhCUaUXYRBjJCFhQm":0,"-L7dhCyqi4tQEMhw19If":0,"-L7dhDT5YIPvFznKuikR":0,"-L7dhDxLfJEA94pcU86o":0,"-L7dhERaG98_DZ1OwHMp":0,"-L7dhEvqkiWjQveHbqUf":0,"-L7dhFQ5PexCeqoAO7gV":0,"-L7dhFuLGrbCz6DdCLgN":0,"-L7dhGO_xBODqAJ3uMmw":0,"-L7dhGspUdz9e46d5ytj":0,"-L7dhHN4j5wz6W4VGNpT":0,"-L7dhHrLV2b2GzafPegZ":0,"-L7dhILZE2Jkpmp636iD":0,"-L7dhIpo4dSeYjFwzlL7":0,"-L7dhJK3-vQzAYUvWefH":0,"-L7dhJoJd9hMlLh9DWst":0,"-L7dhKIZgtf-RZwENCrr":0,"-L7dhKmnCmE1ptXUxsMY":0,"-L7dhLH2tlCZvD9lRWPA":0,"-L7dhLlJvWYlBQ12rImC":0,"-L7dhMFYrMbBTbYIX2rg":0,"-L7dhMjozFfIdY-gF8Wm":0,"-L7dhNE2PysFRwNDFYCw":0,"-L7dhNiINYhRpZ1TPCHd":0,"-L7dhOCYPgHw2s9caf9c":0,"-L7dhOgn13ShcLFU8Qmd":0,"-L7dhPB1NG5dKFYO8xE1":0,"-L7dhPfIiPrgOEBSO_fZ":0,"-L7dhQ9Yt6I_s8NGHTrg":0,"-L7dhQdnUm9HMtZTZkBI":0,"-L7dhR82U6SbuDi8YT3Z":0,"-L7dhRcINTC0OIJbV66B":0,"-L7dhS6YQJORBi7kePE6":0,"-L7dhSan3F9jrKyKdUzT":0,"-L7dhT51KU6XTynqJG58":0,"-L7dhT_HTw23VoU-S6Gp":0,"-L7dhU3Xxo17zVNzNMqf":0,"-L7dhUYmhYT2GR-GkUQh":0,"-L7dhV21lT-ZX6rCvkPK":0,"-L7dhVXHJ64I6yh9zomH":0,"-L7dhW0XRF5ZML2bOobQ":0,"-L7dhWVm9yWXCyHV5c0i":0,"-L7dhX-001L0dYxsxcYj":0,"-L7dhXUGi3R1IQ87VLwT":0,"-L7dhXyXdhXbwXbNeSwQ":0,"-L7dhYSm60zxNdT8xrEN":0,"-L7dhYx0PZPUw2Qa9z1u":0,"-L7dhZRH6KsCmyd_HK7D":0,"-L7dhZvXXQUKkAohWXaD":0,"-L7dh_PmKBhjE-apnsHU":0,"-L7dh_u0eTWyni_8iOya":0,"-L7dhaOGV0KEINU_DRLj":0,"-L7dhasWh-zd5gUAVDo2":0,"-L7dhbMlXuciutlb4oMh":0,"-L7dhbr0jQookXD3TRVr":0,"-L7dhcLHybLNcuT5Ga7U":0,"-L7dhcpWthaD_OvcJgvE":0,"-L7dhdJlC5NX3C3UZAwr":0,"-L7dhdo08ZAwfEiTtPvz":0,"-L7dheIGvjv2Dgh_IVbK":0,"-L7dhemWHdwcWCJSvaWb":0,"-L7dhfGlsBUWFqo2VFpu":0,"-L7dhfl0-aCGAeuA-BYT":0,"-L7dhgFGy3KjdXM_cDQe":0,"-L7dhgjWAPrxPDhBkOqO":0,"-L7dhhDloVnDk-7YpfEp":0,"-L7dhhi1CLd_-GygU-kx":0,"-L7dhiCFBNKsVe1V9Lz6":0,"-L7dhigWDHlVxLysXvtN":0,"-L7dhjAl1KB0ZdJALnFA":0,"-L7dhjf-uvp81DDmV6eW":0,"-L7dhk9FeLlVglO2Y8l6":0,"-L7dhkdV0C_rfuKQeppV":0,"-L7dhl7kn6he8xwTNTu0":0,"-L7dhlc-G6KkUd8KHsud":0,"-L7dhm6FjUt64K6xTG9e":0,"-L7dhmaVND_MrTdN0TNh":0,"-L7dhn4kWnCAiI6wGH5Q":0,"-L7dhn_-Ifo6TJMFEyAm":0,"-L7dho3FjoLnCAAfRqd3":0,"-L7dhoYVq6NVi0x5Er7F":0,"-L7dhp1k3QaRp182rCRB":0,"-L7dhpX-r3WxSnVGs7xm":0,"-L7dhq0EBC0t9CDonMq5":0,"-L7dhqVVWCmn5RNUVCwr":0,"-L7dhqzkEuAMy7UnDOXg":0,"-L7dhrU-c-XYANM7WbxK":0,"-L7dhryEg2yyn1m0Wd9u":0,"-L7dhsSU7fVbpZPY4qnO":0,"-L7dhswjybFxC0K7pJHd":0,"-L7dhtQzmUPwvImEJF1C":0,"-L7dhtvEe_q2RAzEt9go":0,"-L7dhuPUGQtxtupAeCxN":0,"-L7dhutj3PhavsGVgtmN":0,"-L7dhvNzmFVSpPcSYb_-":0,"-L7dhvsEyHsypL--pQVy":0,"-L7dhwMUveVENTZ5c-lk":0,"-L7dhwqjhhlUjo8nY6a9":0,"-L7dhxKzomjt8r2CvACj":0,"-L7dhxpEuMQldtuH0RNv":0,"-L7dhyJTTLqnRayX70Ap":0,"-L7dhynjJg7LDCnpybs6":0,"-L7dhzHyvKFw7bUD1VK5":0,"-L7dhzmDaOoIqYtgX4N3":0,"-L7di-GT2T9HjkxKFN1u":0,"-L7di-kjZBj2XcVqjkd4":0,"-L7di0Ey9OJXP2y4Clss":0,"-L7di0jDKzeKZdWiC_ww":0,"-L7di1DTVjckJWgbkyQy":0,"-L7di1hiRHYv0IUIzhbf":0,"-L7di2BycYcuqRCMLeXK":0,"-L7di2gDXfBI-VLGIbiP":0,"-L7di3ATmkMvkf47oVWy":0,"-L7di3ehOib1TtKT4XKz":0,"-L7di48yZREAebsb4cRi":0,"-L7di4dEzF5Qud_-m0_G":0,"-L7di57TdW-APvLD87yI":0,"-L7di5bigA9UU21zHaDi":0,"-L7di65ypnhagdo5gK9f":0,"-L7di6aCgggsgKKluXUb":0,"-L7di74Sv_yZHdvziIeK":0,"-L7di7Zh2pkFWBqtmN9y":0,"-L7di82xDXQiM1xVoHP5":0,"-L7di8YCb0iUtStsMdTL":0,"-L7di91S0N_RjePT7qaE":0,"-L7di9WhVWbQGsIVs1AA":0,"-L7diA-xgt3ehFExxrU1":0,"-L7diAVC0UatGSWbnzd8":0,"-L7diAzSaePl-RkrEiPF":0,"-L7diBThJiomfontlRkD":0,"-L7diBxwVkl_xCccLjRo":0,"-L7diCSCHnLnNiubBGkJ":0,"-L7diCwSUuVDMLdWGw1x":0,"-L7diDQgAo5qnAMQSJR4":0,"-L7diDuxp3qpgKWB0A8h":0,"-L7diEPDxpvazltrzZvR":0,"-L7diEtSIk4EwL7GLqU5":0,"-L7diFNhMAjhquQNn7IV":0,"-L7diFrx6o9OM0qVFl-x":0,"-L7diGMC4NT9RVX_CCRb":0,"-L7diGqRkRlDxRDnjrm5":0,"-L7diHKgB3NjETQq5dII":0,"-L7diHowYXXSiOwnVjqk":0,"-L7diIJBARBu3XNZwXwl":0,"-L7diInRoSzaZxEKVduf":0,"-L7diJHgW93Gd0slC-Ue":0,"-L7diJlwJi6lrbQrCcBw":0,"-L7diKGB82YYJoB6nY3W":0,"-L7diKkRQxJEpUs71lqe":0,"-L7diLEgTD9eweHDq_kb":0,"-L7diLiwJH85_k14Cl60":0,"-L7diMDAGGxLiRrlWxHd":0,"-L7diMhRRAjXiC-V68zn":0,"-L7diNBgw1KMUCkxkvC8":0,"-L7diNfwkHqN0Q1imq_g":0,"-L7diOABJ4nPeTXHNvOi":0,"-L7diOeQQhZENXZXCkAr":0,"-L7diP8fx3g3gn_IF6-Z":0,"-L7diPcwgNz3gsauwdcm":0,"-L7diQ7ACYN5B2oomHvM":0,"-L7diQbRDyP5JGUaC4F2":0,"-L7diR5fr8vZ75ciURFE":0,"-L7diR_ugFWDfua5eE3S":0,"-L7diS4BOBKfJsZIvKA7":0,"-L7diSZQ5UegfaKWwPwn":0,"-L7diT2fsnDzQ8HDwvDm":0,"-L7diTXvK1fDxvDGZQuA":0,"-L7diU1AGqyOqgilB1gI":0,"-L7diUWQiqXCR0F-siu9":0,"-L7diV-fdqfKV6Hnz6XK":0,"-L7diVUvYvT27Yamhbb6":0,"-L7diVzA3fZ_KwQBYr6m":0,"-L7diWTPpV_U-Mz_zPpE":0,"-L7diWxfQTqBqGmzLzHa":0,"-L7diXRuVM0OU05kO3tA":0,"-L7diXwAbWLO8xBu3R8_":0,"-L7diYQQFj0g576ssqIy":0,"-L7diYueFW31Ctuk_Hlh":0,"-L7diZOui0-KtHv468nR":0,"-L7diZt90tWv-NskITn5":0,"-L7di_NQaMD9WT3Yaack":0,"-L7di_reh_7M00dVr9Sy":0,"-L7diaLuAs34lKV259Wx":0,"-L7diaq8h4WS3Od85TFM":0,"-L7dibKP6gqztFyA01_i":0,"-L7diboeDxeqIxcDFExG":0,"-L7dicIuXdpN3W8BqEzu":0,"-L7dicn9KzndsY0HBd0j":0,"-L7didHPOyUlGyJ7gXjH":0,"-L7didldQOnQjv8VS2Rs":0,"-L7dieFtvK9CnobXKkfj":0,"-L7diek9MoHpZRBQQlPU":0,"-L7difEOLg9Z9ti0W1ol":0,"-L7difid66mNv3M4w0io":0,"-L7digCvIPAHyvutF9Db":0,"-L7digh76vuWWnrRk0j9":0,"-L7dihBOtW9NAFYqs5X-":0,"-L7dihfdso9TfXUzpVkc":0,"-L7dii9u1zjhiRGcYGUS":0,"-L7diie89ad6HkApTE_l":0,"-L7dij8Odq_VzjYG2qQg":0,"-L7dijcdBbDiYCm1GOVd":0,"-L7dik6tlNFUTVp1Qu6y":0,"-L7dikb8Vp5pIoE1KVnf":0,"-L7dil5P3D_ke3EtKM3I":0,"-L7dil_dARVcPh_BqCLC":0,"-L7dim3txw47ZDZTrmga":0,"-L7dimZ7wgCnkacFreiH":0,"-L7din2NNPTOzkFDOmlg":0,"-L7dinXdJ14JuhGnU9Wu":0,"-L7dio0tcsiHXTzj014p":0,"-L7dioW8u91_NPFVNZah":0,"-L7dip-NAIMmcwWpxNLj":0,"-L7dipUdpbupKzss-Osr":0,"-L7dipyskd_1LamykDsR":0,"-L7diqT7WLgrmzoXMo3r":0,"-L7diqxNCrkiWwlluJ1W":0,"-L7dirRcGEwSiYacOiu8":0,"-L7dirvsptUP647It1RB":0,"-L7disQ7rJrWtvDaTYJX":8,"-L7disuN3J5jxqJA8w5K":14,"-L7ditOco-Kw25PyToAW":14,"-L7ditsrh-qBS61iglHi":14,"-L7diuN6G7jFB7a-2oTK":14,"-L7diurM-yRMjmvTJm6T":14,"-L7divLcqSnVeIJDuCQk":14,"-L7divpsC-f6A7rs1-LT":14,"-L7diwK7BxghvP_yT-CK":0,"-L7diwoMW5YfAztlzDdq":0,"-L7dixIb10WUofZCBG6S":0,"-L7dixms3CPdb2eseo0W":0,"-L7diyH6rPeKPUHM_Spn":0,"-L7diylM-K1rSdKJG1Kl":0,"-L7dizFbYO07Bp06-k7T":0,"-L7dizjqUSZQkjjUEx0u":0,"-L7dj-E67oYdNiuZ8hLW":0,"-L7dj-iMFbam9DH7sSbv":0,"-L7dj0Cb8LD8EXFyoaBa":0,"-L7dj0gr1Zw1MoPq2res":0,"-L7dj1B5mtDTwvh97xGl":0,"-L7dj1fLwZTC5JZqxZXz":0,"-L7dj29bvZH3RdXtgKrV":0,"-L7dj2drkvew3tXc0T1V":0,"-L7dj386cAg-hWb3VRZR":0,"-L7dj3cMXYut8J5pMzyr":0,"-L7dj46b51nMqnAmPh4F":0,"-L7dj4arCGn2syybmqEu":0,"-L7dj556U_Rfo7CYI1wq":0,"-L7dj5_LXFwNt5NbESg_":0,"-L7dj63atr65Ie4zGVO9":0,"-L7dj6YqhHFRQ4ByjABK":0,"-L7dj725wyWmOAObaQIG":0,"-L7dj7XLrkAnltDfsnnB":0,"-L7dj80aT9JHmOkbhynf":0,"-L7dj8VqFwzvz6qR6gnl":0,"-L7dj9-5IiEWZTYDPiUD":0,"-L7dj9UKZcI1C_sLbmFD":0,"-L7dj9y_4Qe31leemAHu":0,"-L7djASqI87MB2gjCtW8":0,"-L7djAx5NgOfgJhxM_t4":0,"-L7djBRL44pHGkPs9F6W":0,"-L7djBvawtyqNU6LKgix":0,"-L7djCPqHG7X9pbolQnV":0,"-L7djCu5aZi0Jldrm7qp":0,"-L7djDOLeZz2ehnsnkNX":0,"-L7djDs_RiAsiD4bo-Y5":0,"-L7djEMpTLKAdUhAf2T5":0,"-L7djEr4zq1l3GO0bW2d":0,"-L7djFLK4dIsIDxO19-x":0,"-L7djFp_5TPxWKfHumLr":0,"-L7djGJpP0wpsj_49Pww":0,"-L7djGo4fa3BwMSDypSe":0,"-L7djHIKAj1LOLZb7Sgp":0,"-L7djHmZCHkC1u3enb-j":0,"-L7djIGp8_NIqjEUmglf":0,"-L7djIl3PU4C5X8HC7nR":0,"-L7djJFJ0RZbyh8r9_mP":0,"-L7djJj_n_X7cQOMPHNc":0,"-L7djKDpJqj4fL9icoRE":0,"-L7djKi4AUEhr0D4RjJK":0,"-L7djLCKVptApkKfhsQi":0,"-L7djLg_zeiG-GPI4oBR":0,"-L7djMAoVHQ-0qslquoD":0,"-L7djMf3Y9ou24OTeNvI":0,"-L7djN9JZnz-Dp7XwnoA":0,"-L7djNdZ7fQkukVWfBCJ":0,"-L7djO7nPqq51aNVHFy_":0,"-L7djOc3iWaMsEm68vJ0":0,"-L7djP6J7idW66gfftHy":0,"-L7djPaYBn2glbfETUwk":0,"-L7djQ4nm6WCuf0xyMZu":0,"-L7djQ_3bDClz2SJ8lWM":0,"-L7djR3J0DOFHJqZnbxF":0,"-L7djRYZj8LjF5QOpe5d":0,"-L7djS1oXnT1EVrwnlRD":0,"-L7djSX2rR9GAtaKP13W":0,"-L7djT0JBhTvzWi_c8TY":0,"-L7djTVZmpUvW_CQ769Z":0,"-L7djTznWMrSCzprnEGY":0,"-L7djUU20NoQJ4GXil1M":0,"-L7djUyJhLATd6flefnn":0,"-L7djVSY-ekuWZDalYvb":0,"-L7djVwnXMBM30VPGdRo":0,"-L7djWR2vN9YPinxcSO_":0,"-L7djWvHAByMQ5bma4Hn":0,"-L7djXPYGIH3e-gQKneh":0,"-L7djXtmipIpD5NiFsbE":0,"-L7djYO1XDVgOuchvIAB":0,"-L7djYsITG5NmifYWyMy":0,"-L7djZMY8B9Jk2n2buY6":0,"-L7djZqndGYG-LMGx0y_":0,"-L7dj_L1cUT6k6P5JZJY":0,"-L7dj_pHCt2Dqv-_wAJz":0,"-L7djaJYUd0zV4jUwno6":0,"-L7djannvuca5ZMjEr-x":0,"-L7djbI1rbj1yXbTN2EG":0,"-L7djbmHvB0lv9khGoVG":0,"-L7djcGXX4N0MYCtw9gs":0,"-L7djckmmASbKVIpCKqj":0,"-L7djdF1rKkHp57qUNXM":0,"-L7djdjI9MnTvu24_uol":0,"-L7djeDX7_IMvdqdezMU":0,"-L7djehnZLptQnbJ0EOS":0,"-L7djfC0fuqoF-wU0hUV":0,"-L7djfgGeiFPXKqwtz4h":0,"-L7djgAXYqHgw_wjW8qE":0,"-L7djgem1uG3JHL3k_Ho":0,"-L7djh91Pzl-fbZTR3Oh":0,"-L7djhdG6OqnmExZO95x":0,"-L7dji7XIwWGYFcLcQZ5":0,"-L7djibmgT5LBlP1qVOE":0,"-L7djj61pB4X0RFofSPx":0,"-L7djjaGezFAU2dV3ZcU":0,"-L7djk4Wr1RQdWLfEvb1":0,"-L7djkZllLijbjFTFbTW":0,"-L7djl30Z8onifMgXjy7":0,"-L7djlYGxDujp3Q6ETyn":0,"-L7djm1WBnkFTSRMQHoN":0,"-L7djmWl9yj8YkpKnojS":0,"-L7djn0-iiBLWWGu4Ree":0,"-L7djnVF7jLfBD2USzJ-":0,"-L7djnzWFpTpftwe1UzZ":0,"-L7djoTlPM04BcsOdBnY":0,"-L7djoy0I7CoCM2875RA":0,"-L7djpSFyOAgOLr1NmQ1":0,"-L7djpwWz11kwMSfAkae":0,"-L7djqQlDtG_qmnmJPMq":0,"-L7djqv0Q0MlFv06hr63":0,"-L7djrPFOSFXQslTLaMP":0,"-L7djrtVtgz_TuoFtQMo":0,"-L7djsNkI-W5UXvHNlac":0,"-L7djss-xbb5dDIAUcGP":0,"-L7djtMFDMWeMZ0KtA87":0,"-L7djtqV44SFE4QkabRe":0,"-L7djuKke2X3vQYDLXX7":0,"-L7djup-I-5WGby7MbPb":0,"-L7djvJF237M8UASw6T1":0,"-L7djvnVwDClbplNKm0k":0,"-L7djwHkPNC51qX0gR5G":0,"-L7djwm-l4M3QTRO6rxV":0,"-L7djxGESBohcvItBTsL":0,"-L7djxkVbq70oDLLweIy":0,"-L7djyEkdRGNMtm5Fn2-":0,"-L7djyj-krdmE18iM1Gt":0,"-L7djzDFeAlZ3iUS8TA5":0,"-L7djzhU7wF5dbNlJBAf":0,"-L7dk-BkgPW2-eGXmO9V":0,"-L7dk-g-FB5We9dRDsZn":0,"-L7dk0AFQAyEOcc2RQSL":0,"-L7dk0eU9LKqTpgMCOh3":0,"-L7dk18j6BM4Tv17l1GT":0,"-L7dk1czL7PmoiJdIEAu":0,"-L7dk27ELdqExSGiQFr5":0,"-L7dk2bUi4bAg-TZYuLE":0,"-L7dk35jnmc1yrsAxfiq":0,"-L7dk3_zk5wy26gC-tYY":0,"-L7dk44E0XipHdQLmdKu":0,"-L7dk4ZUZdcMZE92yPxZ":0,"-L7dk52jKs23dKJdrH86":0,"-L7dk5Y-G3NyEzDigNy8":0,"-L7dk61EVc2vtMANVu3z":0,"-L7dk6WTBCH-phvvULrc":0,"-L7dk7-iRZICgq1SnG-n":0,"-L7dk7Uz3u9e4Fj6kt4e":0,"-L7dk7zDZBu8a6ku-K3w":0,"-L7dk8TTET07VH9kiMv4":0,"-L7dk8xisHbKZ1T1utW6":0,"-L7dk9RyqTDUPY5kT3qy":0,"-L7dk9wDz5NTH0VnY5ga":0,"-L7dkAQSp21X_c7XQMo-":0,"-L7dkAui1QlhTlL3JBXa":0,"-L7dkBOyA9VNIZ6JcZox":0,"-L7dkBtDy-B0S7KHM4KS":0,"-L7dkCNT2oq8CPmSpPwn":0,"-L7dkCri7YQjbT6V6wUh":0,"-L7dkDLy9uiN98I_PCYm":0,"-L7dkDqDFs94dZwIeDRr":0,"-L7dkEKTi81k6vDtSQ4F":0,"-L7dkEoi5o-dswmjDfGu":0,"-L7dkFIxQ41B3Obp06E2":0,"-L7dkFnCFNbGZ3yRMcwF":0,"-L7dkGHTjyu0IeJuF4VO":0,"-L7dkGlhMi_86r34Snuj":0,"-L7dkHFyVxiE8eJ_2VSe":0,"-L7dkHkCtalQ3Bz6sJon":0,"-L7dkIESbvwd8RL5SQcS":0,"-L7dkIih2VaKw4VrLhRP":0,"-L7dkJCxrxirmlvQzdwZ":0,"-L7dkJhCxyr5qdFUJYVh":0,"-L7dkKBSNCfviJhVZSXZ":0,"-L7dkKfhK9-7as6MGrPo":0,"-L7dkL9yjKrvIK6znhw4":0,"-L7dkLeCg2e7PlNnhaGr":0,"-L7dkM8SrfRfsT1qsgcl":0,"-L7dkMchjSqgBUE6loRW":0,"-L7dkN6xbXQr7ZnOv8NC":0,"-L7dkNbCMFn5xX9yJbLM":0,"-L7dkO5SbrEUoSZ1nGWt":0,"-L7dkO_hEMMnsnadN_0W":0,"-L7dkP3wXOSTOQRklAqW":0,"-L7dkPZCCaYreqhA1cpW":0,"-L7dkQ2Rg1zn5e6uT3kQ":0,"-L7dkQXgKYt8j_WuasVc":0,"-L7dkR0vex6F8bO4qRRy":0,"-L7dkRWBgPniyy9QGMkj":0,"-L7dkS-RGCkNkNH86MGK":0,"-L7dkSUgZ0xjfHDBVZCt":0,"-L7dkSywT5sw-DfUijIi":0,"-L7dkTTB15Zqv73gDcQe":0,"-L7dkTxR62UC0gcPSvOj":0,"-L7dkURgF6p7JSn6GZDM":0,"-L7dkUvvQfEPn9Guna0l":0,"-L7dkVQBpKSOoD8Oh6qm":0,"-L7dkVuR9d2d5_I8fWty":0,"-L7dkWOgwQtg73HeScL2":0,"-L7dkWsw6YIaCx3gj7F0":0,"-L7dkXNB6FR8yDkrcV4K":0,"-L7dkXrRc3JbliK_vt6-":0,"-L7dkYLfHsu1jV2i2Rpm":0,"-L7dkYpvEmv3BWa3Wmy_":0,"-L7dkZKA6QOtiesdhrg1":0,"-L7dkZoQKcsGaLVa5Df1":0,"-L7dk_IfFEYAh3CG6GdD":0,"-L7dk_mvULkLkWDdGqGe":0,"-L7dkaHARVRh8CRRbBfe":0,"-L7dkalQlZ4addSTmkTQ":0,"-L7dkbFf65qoCMuZc-sr":0,"-L7dkbjuBMmXHRhDHIJe":0,"-L7dkcE9HPlo-azxkeTo":0,"-L7dkciQezBfjeKyDbKe":0,"-L7dkdCewwckwoO-4ZLp":0,"-L7dkdguYSLGAot8w7bM":0,"-L7dkeB9Hfp7ajPu0hBI":0,"-L7dkefPuHLaQukKalsH":0,"-L7dkf9eo6L0VD9eh9CL":0,"-L7dkfduGydMP_CnR5n2":0,"-L7dkg89nSbKi88BAKsm":0,"-L7dkgcPX7FXPkjiSaUr":0,"-L7dkh6dCRnI33EfkokY":0,"-L7dkhauraJ086fjILDz":0,"-L7dki58JH9eWMsODd63":0,"-L7dki_P4e4vdhuaspFd":0,"-L7dkj3evUSKIGgJ-iYg":0,"-L7dkjYu53sXRSF0axEk":0,"-L7dkk29MyfIiFW0eGsg":0,"-L7dkkXPzbN3Sj6Kh9kj":0,"-L7dkl0eGVCbIRsrSfBl":0,"-L7dklVuwlF9Y5qdzFIg":0,"-L7dkm-8OJCBLMzKUOwX":0,"-L7dkmUPkLghfEbfbodR":0,"-L7dkmye4HSbAtNlJ0bH":0,"-L7dknSu9HasNw1FvTtu":0,"-L7dknx9EEDbNbfjO27-":0,"-L7dkoROhh4D7Xf4GPRT":0,"-L7dkovdS3cCYhd4wJ_c":0,"-L7dkpPuwAtvQ-k2D_82":0,"-L7dkpu8Fgxu-THH4vAy":0,"-L7dkqOO3zTWEbyx06es":0,"-L7dkqsdqdnr0StA0C1I":0,"-L7dkrMtsqj11ZjJCuik":0,"-L7dkrr8mbPUUZVg568j":0,"-L7dksLOWJ9LyS7mpHI2":0,"-L7dkspdT2SLnPAIhtVc":0,"-L7dktJtdx3esP45V_cb":0,"-L7dkto8SN9tLUOQiQAW":0,"-L7dkuIO5bsIaq7JRaJV":0,"-L7dkumdBV5-Ci9_1p6Z":0,"-L7dkvGsJ4038KNhZVqs":0,"-L7dkvl8cmz8yWAPdfES":0,"-L7dkwFOL3Lj65erwrZ_":0,"-L7dkwjd2xGRqC9tIDjO":0,"-L7dkxDsxzaQcB9LVGvp":0,"-L7dkxi769X7OGD2gdSQ":0,"-L7dkyCN2kGW2S4jmDAo":0,"-L7dkygc70Iv2Cm9UI18":0,"-L7dkzAsCa1xSNqaVwy_":0,"-L7dkzf7JL0Xr8Fn38lZ":0,"-L7dl-9MpwvJ9QwoFx6m":0,"-L7dl-dch3awJLyDf856":0,"-L7dl07sZ1gbybmriN7s":0,"-L7dl0c7tkcJtkJQap_x":0,"-L7dl16NgKy89FzA5b2j":0,"-L7dl1abVPyAANZIszrn":0,"-L7dl24rw4yaKc1IoiE0":0,"-L7dl2_7dTX-oj-UEEMj":0,"-L7dl33Mksng9An5TnTR":0,"-L7dl3YbygU8lYdeweo4":0,"-L7dl41raNYrX_mvBoPF":0,"-L7dl4X6IEAPDHdIg5cb":0,"-L7dl50M6L4QbnvgtDa2":0,"-L7dl5Vb2uRHuDrBkQrT":0,"-L7dl5zrYJrLS_-X6AxW":0,"-L7dl6U6Ni5ziE5cnmYv":0,"-L7dl6yMnDsMnhXtXK-c":0,"-L7dl7SbQxL-AFD8eWJH":0,"-L7dl7wrso0QOUCnkZlz":0,"-L7dl8R6ZNjLxxxYCAw9":0,"-L7dl8vLmsjpFBFEyhXk":0,"-L7dl9Pa35OzbNb-vXzg":0,"-L7dl9tqH1FpZzIo-tlX":0,"-L7dlAO5Dd1Sm-H3CJXV":0,"-L7dlAsLS2CvZWlcfv00":0,"-L7dlBMbtSk8V7hRwZ1t":0,"-L7dlBqrfXjwbVFTXAn6":0,"-L7dlCL6PBmHCTLBzEjS":0,"-L7dlCpLkjO2J5HnH7Na":0,"-L7dlDJasPL_e0BtbCba":0,"-L7dlDnq4XpJ2GmLggHI":0,"-L7dlEI5xBvhuZy1y4tM":0,"-L7dlEmLGRvsJJoa_6uE":0,"-L7dlFG_Cinnk63DPE5P":0,"-L7dlFkqoz_FBvuUa9kv":0,"-L7dlGF4XjoKU3ea9YpK":0,"-L7dlGjLbmNngudAKfxD":0,"-L7dlHD_4ti89YDyLDYC":0,"-L7dlHhpE3T30bZ3R7U-":0,"-L7dlIC5Mss-zQG7Y6GM":0,"-L7dlIgLQJE5iyih09BA":0,"-L7dlJA_vmA6BWVZ17Cs":0,"-L7dlJequwHjNmgbFnCx":0,"-L7dlK954jyTjkU6t9e_":0,"-L7dlKdKZE7CcdljLUZQ":0,"-L7dlL7_ti8BNFKQwn5M":0,"-L7dlLbpezQf-yvft3qc":0,"-L7dlM64z-jTHOqzpJsU":0,"-L7dlMaK0m0_HhvYtyy6":0,"-L7dlN4_eboWCYxQQiAJ":0,"-L7dlNZpBnJa0x95hMbh":0,"-L7dlO34SS5om7rQPFTU":0,"-L7dlOYKnUz6erKmIYWt":0,"-L7dlP1_xAewqtrHo4R4":0,"-L7dlPWpQF7tXdr11oM4":0,"-L7dlQ03dN7qsoJFawcT":0,"-L7dlQVJwJ4XIzQKNK8I":0,"-L7dlQzZw_ooE24hK8xI":0,"-L7dlRTpsrEI6XGKJUSr":0,"-L7dlRy4Jx6D02CfCkOz":0,"-L7dlSSKbm7G6a_DssTP":0,"-L7dlSwZ-qb_fdPf3C-7":0,"-L7dlTQprbYjqvwHYvCh":0,"-L7dlTv389vhkjSzxsbS":0,"-L7dlUPJe-urSOF9-dkG":0,"-L7dlUtZD9Lt2Y5ddArT":0,"-L7dlVNnCoZuuUJDLl90":0,"-L7dlVs3FQL-GXZil1nF":0,"-L7dlWMJQRaTjX_0Y4qm":0,"-L7dlWqZuHUIn0rBIQc8":0,"-L7dlXKoP75gcmFj4mJt":0,"-L7dlXp3nNzhjk4V2le_":0,"-L7dlYJJSzI3DT0BDuu0":0,"-L7dlYnYPsERKhg0n6eo":0,"-L7dlZHn3dL4hS6QXTOH":0,"-L7dlZm2d_zp3gOCTZsy":0,"-L7dl_GJHquJ7dXs0IrQ":0,"-L7dl_kZZB6A-KdKSD5g":0,"-L7dlaEnGZptNNHPJ9yc":0,"-L7dlaj2TtMoespF5OGz":0,"-L7dlbDJ-Ujm0mVR8BoD":0,"-L7dlbhZUnJUDOEKd4Qm":0,"-L7dlcBnUmeuCp7poaRE":0,"-L7dlcg2YhRvQG3LQZys":0,"-L7dldAIm3MNifDTC44y":0,"-L7dldeYMTWVfH6vj7PQ":0,"-L7dle8nbm1XE6Zwmeto":0,"-L7dled2TZW9se6eXx9B":0,"-L7dlf7IJvoM0s4gJHar":0,"-L7dlfbYDwgrEepc5sYI":0,"-L7dlg5mAqiiWKPnllWX":0,"-L7dlga13QXyXQlrEc5c":0,"-L7dlh4IRc-hD8_BOUoO":0,"-L7dlhZYoZ3XbCtfYmtZ":0,"-L7dli2oDs6AROUEqpA5":0,"-L7dliY4GP3MwuCgVBDB":0,"-L7dlj1O2X4hWqJMpAfw":0,"-L7dljWiJaaVvF_hLj5E":0,"-L7dlk01v9lYxaDQJ_Av":0,"-L7dlkVKCcMXOSgq6muh":0,"-L7dlkzb51P2OEZzOrZ0":0,"-L7dllTuLKtGOQWOFQrK":0,"-L7dllyBmEyKcsxY-ckm":0,"-L7dlmSSyRjUsud7rGKI":0,"-L7dlmwjzJormFmd6UeY":0,"-L7dlnR0WPKJ50J3rmJn":0,"-L7dlnvHnXT8C7fCKUNi":0,"-L7dloPXYkemd4Mg6n26":0,"-L7dlotoxU1LKTisIt6j":0,"-L7dlpO4nOepCskaeogy":0,"-L7dlpsLR8pUWvGoi6vC":0,"-L7dlqMa5KxT0vY-VCUw":0,"-L7dlqqrdOX9P5VRo9Eb":0,"-L7dlrL6gKQmxchMkZrV":0,"-L7dlrpNZ5dylKBamBxW":0,"-L7dlsJcXJNrHGgXNN9W":0,"-L7dlsnsPsZdOGqFa59H":0,"-L7dltI7-WgM-rGo9QnK":0,"-L7dltmO8xEu8VXDiOOA":0,"-L7dluGd4g2l1Xj2kL1y":0,"-L7dlukt-iEQ3sjye_kd":0,"-L7dlvF9XXTj9gBNH7Of":0,"-L7dlvjOLiXO_1QNI6Uu":0,"-L7dlwDdvFz9sq8jlSNI":0,"-L7dlwhtlKQK-5E_R1eZ":0,"-L7dlxC8YUpyBrLujMu_":0,"-L7dlxgPrWFsOODJtnGK":0,"-L7dlyAeq_N_gHzdzEiA":0,"-L7dlyeuHUizZjxd3uMa":0,"-L7dlz99HzCANO4cIXhD":0,"-L7dlzdPbDPiBJXwqHnS":0,"-L7dm-7empbBgvlI4meC":0,"-L7dm-btncQOObAI5qMj":0,"-L7dm068OmiwXamcJ157":0,"-L7dm0aPoMz9tEcf_Cy9":0,"-L7dm14eCpYaQjCM_p0l":0,"-L7dm1ZtbsMaozM_fTW2":0,"-L7dm238nCzqbCv-K5YC":0,"-L7dm2YOKPv9b_QgCbzN":0,"-L7dm31d-uMTfLX2ishq":0,"-L7dm3WtrdxQDFvHkH3F":0,"-L7dm408wASh1Ey7qxzU":0,"-L7dm4VOemNB0ikXSTq9":0,"-L7dm4zd0iKWCi_0PjGU":0,"-L7dm5TtIiPL7xJ8mMU2":0,"-L7dm5y8xGbIu-p6e4bs":0,"-L7dm6SOEmOmdHNJM4qQ":0,"-L7dm6wduDTLWHekFf72":0,"-L7dm7Qt8sROvGWne6X5":0,"-L7dm7v8bXAjdlJpbVFr":0,"-L7dm8PNqm6zjCET7SXM":0,"-L7dm8tdIFNKfkrxQ0gX":0,"-L7dm9NtUo9yFT9JdiBI":0,"-L7dm9s7P3KSmKoWWvtg":0,"-L7dmAMNkNQXld7nf2hc":0,"-L7dmAqcy0nzM8OGDZql":0,"-L7dmBKthX3R74ZaMiKz":0,"-L7dmBp7WvamgUxOUbwo":0,"-L7dmCJN2rX13a6bxo6s":0,"-L7dmCncDm4qEBS5qYLw":0,"-L7dmDHsY8aadVjwKw6C":0,"-L7dmDm7rAJfFDrMzl8x":0,"-L7dmEGNRYyXBDmeeMx1":0,"-L7dmEkcC8ZEDJyIkX9o":0,"-L7dmFEsqCU5cHXrxfur":0,"-L7dmFj7hUCS1p2lCOFf":0,"-L7dmGDNguaQgWUeS2LB":0,"-L7dmGhbQM_bFMzKQQ_0":0,"-L7dmHBs6UVqzZubpDm4":0,"-L7dmHg61pMRYWHqLFsN":0,"-L7dmIAN6Ldd2jIdmXSA":0,"-L7dmIebYrb-1DZjRwNx":0,"-L7dmJ8sJ4k06mmTIyEI":0,"-L7dmJd7-KlsxG2-ly_F":0,"-L7dmK7NhZ76lsCDd_o2":0,"-L7dmKbcMZMc9BJk4rE1":0,"-L7dmL5r8HzglSgXeNCA":0,"-L7dmLa6g_kQnQL11kMa":0,"-L7dmM4MuvanLTwlM8GC":0,"-L7dmMZbPj7u7RUJC6JW":0,"-L7dmN2rFK2TJ1iBMbR1":0,"-L7dmNY6ZnwV-qI_kQqR":0,"-L7dmO1LfKl_kJ4K3YgT":0,"-L7dmOWbe2yL7XI2F3_g":0,"-L7dmP-rvKFNzn_R87AZ":0,"-L7dmPV6IIYdZSISEVlN":0,"-L7dmPzMUnBD0SKR23TX":0,"-L7dmQTabdgxpDE-49Qv":0,"-L7dmQxqcPRADtth8a9L":0,"-L7dmRS5NsqoLLk1x40o":0,"-L7dmRwLdiaeMyBDYY9c":0,"-L7dmSQany3lfbmQyMZs":0,"-L7dmSuqwrK47PRzoTM7":0,"-L7dmTP5EknAMVpgvzCj":0,"-L7dmTtLn0QeXtmKxodx":0,"-L7dmUNaMQjmMy9pF5GX":0,"-L7dmUrqsGci-uVb1rmw":0,"-L7dmVM5D61OYJhTH9T7":0,"-L7dmVqLfAFfqGqBaWm9":0,"-L7dmWKar8Em4pi9p6NC":0,"-L7dmWopNkVNYcnJgqsD":0,"-L7dmXJ5lvtLdM1OP-TG":0,"-L7dmXnLznwy8YR_0Z3M":0,"-L7dmYHayygu_okMdcPG":0,"-L7dmYlq4_nYdF2ljGyN":0,"-L7dmZG4GjioCWo_QgEf":0,"-L7dmZkL99B-ingWtVxG":0,"-L7dm_E_Y41TLgtOogan":0,"-L7dm_ipL5DbR0nmujid":0,"-L7dmaD4ACwyFWmtgn7l":0,"-L7dmahKzvdkkEsVIw6v":0,"-L7dmbB_UJPcnAT3Hzwu":0,"-L7dmbfp_hdORcqULJSj":0,"-L7dmcA4erpEgTKEe4kD":0,"-L7dmceKILxNkv9eD8YX":0,"-L7dmd8_auxNmx_RKE7s":0,"-L7dmdcpnvsg5DNlnfbC":0,"-L7dme74T1pZZRBeUHBj":0,"-L7dmebKZP280j-px9G-":0,"-L7dmf5_SNOVEoVzJltO":0,"-L7dmf_pwJ-_jTr7wFc8":0,"-L7dmg433o8JYcHOObad":0,"-L7dmgZKzR-L899xrxt5":0,"-L7dmh2_1RibbA8OW9BB":0,"-L7dmhXohvx-QjAqQ3pI":0,"-L7dmi1467vC44v2gt35":0,"-L7dmiWKbVJN1zygsr-X":0,"-L7dmj-Zsp5RaAPhIZLh":0,"-L7dmjUoSEBRJDPs8gPQ":0,"-L7dmjz3vvoWJMyXMsQY":0,"-L7dmkTJhv3swHD_bKgN":0,"-L7dmkxZiQnCNna1O0fD":0,"-L7dmlRnLa8-2__6n9qP":0,"-L7dmlw2QzdmlW0hywuV":0,"-L7dmmQInaEp5Po-DMjO":0,"-L7dmmuZ9aweFGwmWRd7":0,"-L7dmnOoo2w1A6aXq1rs":0,"-L7dmnt3eHah9jJZ2wt0":0,"-L7dmoNJ-uwm4vnsHyzM":0,"-L7dmorZVF0G-9Fjxc_6":0,"-L7dmpLnrt73D0-OgCdc":0,"-L7dmpq2FuxRUGGPXb4G":0,"-L7dmqKJTObf64JCsExf":0,"-L7dmqoY3Axzuvdc3AzB":0,"-L7dmrInQnVIXBoF7AUX":0,"-L7dmrn2BfO1s-8_X3Om":0,"-L7dmsHJafY513AO7DCL":0,"-L7dmslYoTxH2q65EyOA":0,"-L7dmtFn4zmKWosRlNcA":0,"-L7dmtk3dC9M8-8wd-dc":0,"-L7dmuEInzUgLDi4vjYw":0,"-L7dmuiYK-6ZguEpv8Zo":0,"-L7dmvCnTZgT-orBolMF":0,"-L7dmvh2GGTtzvECdnPP":0,"-L7dmwBH8_jVW9XQL80Y":0,"-L7dmwfXOyk1LZwiHxtM":0,"-L7dmx9nuQ1dYSXH3Cu3":0,"-L7dmxe1K92yzpIxj486":0,"-L7dmy8HnikJFlxko-fi":0,"-L7dmycYWK0FUfhtIq8F":0,"-L7dmz6mGFtpVIQq30oc":0,"-L7dmzb1xKixOvzDpGMK":0,"-L7dn-5H-CIDGdHidn6_":0,"-L7dn-_Xp9opn0FeAO5D":0,"-L7dn03mYUy6S-xb98o5":0,"-L7dn0Z22Tt6pMFYvy3Y":0,"-L7dn12HMQEGCtPTkl2F":0,"-L7dn1XXSAsigIwwxhiD":0,"-L7dn20mbDmYiRE29gUu":0,"-L7dn2W1OL28fQh_p2ht":0,"-L7dn3-HjW2Tyx1fna0J":0,"-L7dn3UXhsY2-0ATLi4t":0,"-L7dn3ymhdyTGzLq3kIb":0,"-L7dn4T0fOkXQ-W9q0pE":0,"-L7dn4xH8_n6Yr-yB9qW":0,"-L7dn5RWR8CuX8bqNcJC":0,"-L7dn5vlRSN-YvtL05z2":0,"-L7dn6Q0pb4AV6x70Bom":0,"-L7dn6uGyfPrCYEopG0j":0,"-L7dn7OWcILf4J4E_6jr":0,"-L7dn7slgyFlJjhFcE3J":0,"-L7dn8N0Af6HG3VGYk_N":0,"-L7dn8rGt8VQQ9B7TDwL":0,"-L7dn9LWN7CfbKbtxwmy":0,"-L7dn9plG-lzKJ4IVo_2":0,"-L7dnAK0NLOT5FqaNI2k":0,"-L7dnAoFMnVU6EDSQSib":0,"-L7dnBIW33VB6UBMwhmI":0,"-L7dnBmlmFtHIesyOXN7":0,"-L7dnCH0SyiPWlPRgPb6":0,"-L7dnClGchgnYO0ft9Zo":0,"-L7dnDFWyvm2jQ8Ih5Az":0,"-L7dnDjkDZ4_-XWq6Rmj":0,"-L7dnEE-rMQwtBYNij0M":0,"-L7dnEiF_rT0pj5bUt_T":0,"-L7dnFCVa4MBcd2HvXdv":0,"-L7dnFgk75vg8_-SVyyh":0,"-L7dnGB-x5YS4fHaJdUx":0,"-L7dnGfF3xOe3Tjmaaol":0,"-L7dnH9VO9jcAY8Z87jA":0,"-L7dnHdkNKMKqgRf6xtL":0,"-L7dnI8-ch-fUvE8S519":0,"-L7dnIcFKqaKcPUIfTvn":0,"-L7dnJ6VrqThjUAFsSWW":0,"-L7dnJakS4d8JYrMFwC4":0,"-L7dnK5-3NgQyN5vY88V":0,"-L7dnK_EtcmS6RS5TXyO":0,"-L7dnL3V2otDoW-Tu6FJ":0,"-L7dnLYjp42AqJWAdrp5":0,"-L7dnM1zg4bTKw3tTeYT":0,"-L7dnMXEiCjYerAbAOqF":0,"-L7dnN0U4c5XBLs9Sfsp":0,"-L7dnNVjiv4-ocl924TQ":0,"-L7dnO--9ek1-on3WmEI":0,"-L7dnOUF0z8G8wJDqAP6":0,"-L7dnOyTBdc41zRTEHix":0,"-L7dnPSjP7JsWqsN_7MJ":0,"-L7dnPwznF9LuY0h9l1k":0,"-L7dnQRERKNNhGeZYvMH":0,"-L7dnQvU9tH4HN9y-Qyt":0,"-L7dnRPjimYuQ_Xl6lJt":0,"-L7dnRty2fxWZGqW_pBf":0,"-L7dnSODWEC0RNilgjF2":0,"-L7dnSsUyzFzCcbOnznh":0,"-L7dnTMjIyG4IgfJZZHk":0,"-L7dnTqzC_BG2qcrFQ8s":0,"-L7dnULDORPCHHms8-LI":0,"-L7dnUpTWMPzZC5gpFDP":0,"-L7dnVJiZKxTBVSwToGO":0,"-L7dnVnz84gG9J-5wbcp":0,"-L7dnWID8IGlta9_g5yK":0,"-L7dnWmTQ04XvmIeNlbW":0,"-L7dnXGiSTsKcN7NKA9-":0,"-L7dnXkyxJPy25ddlHxW":0,"-L7dnYFD6wkX3oJXGgON":0,"-L7dnYjTQrVV362auBsD":0,"-L7dnZDiCuuFW4fVu5ST":0,"-L7dnZhy16CnXX6hZTdW":0,"-L7dn_CE4mtkvptzf1Z5":0,"-L7dn_gT0f_NGPXlFglY":0,"-L7dnaAi5YyQMA02B5G6":0,"-L7dnaeyaI-BpqKv78Do":0,"-L7dnb9C0TzxkVyuNtw2":0,"-L7dnbdT3K4AqsFR9do1":0,"-L7dnc7huvV9iumGXSet":0,"-L7dncbxh8qBVSvrFV0K":0,"-L7dnd6CQKV06a_E5MLO":0,"-L7dndaSdDBNkNhixliT":0,"-L7dne4hg5dbtYfS9pme":0,"-L7dneZx6OQ1b-Qn3ZI5":0,"-L7dnf3C2cziS4DAiJWc":0,"-L7dnfYShwrdZ72Q24yR":0,"-L7dng1h0b_xpvr06HCh":0,"-L7dngWxwb5Tk1ZR4Yky":0,"-L7dnh0CDvDk28zZT1Gq":0,"-L7dnhVSgCH9FQaY7f12":0,"-L7dnhzgck1hj4I7DGr7":0,"-L7dniTw8EBuYhiZC9nw":0,"-L7dniyCTG0rI-ycFf12":0,"-L7dnjSRF5rZW1P9j6x-":0,"-L7dnjwgzc864f7mg0CO":0,"-L7dnkQwg8-gm6CYdoiX":0,"-L7dnkvBh4mvYheHoiIs":0,"-L7dnlPRaglxSdCgTRY3":0,"-L7dnltgC_NpfSuDo2Qw":0,"-L7dnmNwvdDY8fCRouL4":0,"-L7dnmsBK6myT0AaG9he":0,"-L7dnnMRuLY7tpFdXqhN":0,"-L7dnnqgyB5eHqETjfcb":0,"-L7dnoKwTrEwsZBxiVxV":0,"-L7dnopBpl3uZzE5N1Yl":0,"-L7dnpJROUzOUj0LYr6V":0,"-L7dnpng4srOwQW9i7dv":0,"-L7dnqHwNGekO8bGRzeW":0,"-L7dnqmAefUA0ds3Wd7O":0,"-L7dnrGQDYeF5B0zDGFH":0,"-L7dnrkfppfZMi2lZKYO":0,"-L7dnsF1QhPZ23misMsm":0,"-L7dnsjAD8VFgqp-nGj2":0,"-L7dntDQWwu1zrYuL7D1":0,"-L7dnthgUb2BYqskoTYu":0,"-L7dnuBvDnDbMmhvJBsA":0,"-L7dnugAh0QgZHz2JibJ":0,"-L7dnvAQ9LmO5aE4q0qW":0,"-L7dnvef9lxNwLMECmw_":0,"-L7dnw8v3YRq5ADGM4LJ":0,"-L7dnwdACASFYx6OQi7y":0,"-L7dnx7Qohz1EHC4odig":0,"-L7dnxbenr0RXokP9DCJ":0,"-L7dny5vPiXC5Ua1LAfr":0,"-L7dnyaAuDcy1yPIK-qw":0,"-L7dnz4PiU5z9UcY5A2A":0,"-L7dnzZelFrBY6hwkwke":0,"-L7do-2uag2zeXMv7rrM":0,"-L7do-Y9ygbFg1vb9Yfu":0,"-L7do01PMPHREQvLjwde":0,"-L7do0We6eF5N6igY_IL":0,"-L7do1-uEck4zaYLCvY-":0,"-L7do1V93tr5k6uIpa4c":0,"-L7do1zPALJiNLObAbQZ":0,"-L7do2TeKOkD2D0OlMzA":0,"-L7do2xutoIRD8wdKeCf":0,"-L7do3S9kHuqIn7d_4ge":0,"-L7do3wPa8mjpCqysbYR":0,"-L7do4Qef3rZGxCFM2iN":0,"-L7do4uuA2ZbJ5jTxGVO":0,"-L7do5P9Z59E_hoyrzk2":0,"-L7do5tPdFmbWP3D9JlB":0,"-L7do6Nd4230rMcmBBhh":0,"-L7do6ru0y_YykhAsumT":0,"-L7do7M96XA7ITls7fYn":0,"-L7do7qO8sF2PSKY2jgG":0,"-L7do8Kd-7rWxtlC26nD":0,"-L7do8ot7_2d9c5XROOE":0,"-L7do9J71MRLNW0pK4YC":0,"-L7do9nOVQKZ-9Umdnoc":0,"-L7doAHdd8F6k54hgrK8":0,"-L7doAltUegRjyPwZeMM":0,"-L7doBG8EaaE3Y0t2-LC":0,"-L7doBkOTTZOKWiJz2Zo":0,"-L7doCEdsIepNmZm_SDA":0,"-L7doCit88ECNxao82lK":0,"-L7doDD8CaT3uuHKENTj":0,"-L7doDhOJOyHLMdz0efd":0,"-L7doEBcO93v0Q6gjvEz":0,"-L7doEfttRAo9FvSC-dT":0,"-L7doFA84HoFcuOopBsc":0,"-L7doFeNbkqyGh1AZuzk":0,"-L7doG8c5VDsTG3hdR-E":0,"-L7doGcs2F_N4E_Tdc4f":0,"-L7doH77xEZKMBcwI69Z":0,"-L7doHbNkfVGaVGn200M":0,"-L7doI5cCrXn8LbawLDk":0,"-L7doI_s8ZLA742UNJc3":0,"-L7doJ47UwsMyS9P_hFV":0,"-L7doJZNEkmTIMireodE":0,"-L7doK2cVZall8R1aCP1":0,"-L7doKXs133_1bLLFEZn":0,"-L7doL17jxJe85GJyB1J":0,"-L7doLWO5FL4oiVqjk99":0,"-L7doM-bI0icpOuqilS1":0,"-L7doMUs79L_qN-gky7W":0,"-L7doMz7h3JxmsbK-MyE":0,"-L7doNTMdUg98XYltjz8":0,"-L7doNxbrXhojowwubFF":0,"-L7doORr1VSwgOE6RX2U":0,"-L7doOw6OR0N05eiH4GD":0,"-L7doPQMq2VKr5uPKW7o":0,"-L7doPub-56C6A_x-eBy":0,"-L7doQOsR_nDCYNf1YSO":0,"-L7doQt6XRJZ98fSkKiR":0,"-L7doRNM2mNfokd7xklE":0,"-L7doRrb3VT-eVn3X4m9":0,"-L7doSLrzM4tU4sREVNJ":0,"-L7doSq6SdzQmDG-tDOk":0,"-L7doTKMn2xjOp63ICez":0,"-L7doTob4WiOHpm_yrzX":0,"-L7doUIr7druPG3Zab7l":0,"-L7doUn6YTKPnrRnpkEa":0,"-L7doVHLA6e6_WGjThi0":0,"-L7doVlbpLTSrqhX7dOP":0,"-L7doWFr3vr9JLqFAdin":0,"-L7doWk6IMbtj8al3-ON":0,"-L7doXELl2mTao-OKMfi":0,"-L7doXiaARSUc7zh3Lgy":0,"-L7doYCpC8sZpeaZ3rRU":0,"-L7doYh52LgVNw444DQa":0,"-L7doZBL78vQwC9FNNDX":0,"-L7doZfaK9KyLbs0nAxX":0,"-L7do_9q_N0jPBuYNKsb":0,"-L7do_e5a7vG7ARpjT8o":0,"-L7doa8LnvOpon8MnG5Q":0,"-L7doacazHjUjUopwa-A":0,"-L7dob6pHlC3BhtXiZAc":0,"-L7dobb5del5BBeO4N8D":0,"-L7doc5Km5wX1kEjGW2F":0,"-L7doc_a1CSWk_AB3tXx":0,"-L7dod3q5gFC_3eh4c0-":0,"-L7dodZ5me7iOH6vEns3":0,"-L7doe2LZvicU6w-bQ-A":0,"-L7doeX_dP6yi3H3Ila1":0,"-L7dof0pTDB7qe2EO3bu":0,"-L7dofW5nrpnEkf2kQll":0,"-L7dog-KHpiZmI75UiEx":0,"-L7dogU_ip44_GGhciUB":0,"-L7dogypV241wzALCvlK":0,"-L7dohT4_laffcUsT1OB":0,"-L7dohxKIbvkuJ8IpXmp":0,"-L7doiR_0EE8phRD5Kp5":0,"-L7doivpmZR6WJZvZ49C":0,"-L7dojQ4JR_769hEsw-s":0,"-L7dojuKYgpbTFiVZUtv":0,"-L7dokOZcfPp_Ml38Ba4":0,"-L7dokspVUpCZB7yCFpK":0,"-L7dolN3SIu6sWRayPf-":0,"-L7dolrJxsGcjZVsL2Ib":0,"-L7domLZU6AKscAE1lRr":0,"-L7dompo06-aKYNGBtPZ":0,"-L7donK39WiNgs-NxcYa":0,"-L7donoJgvGh4c29FM4d":0,"-L7dooIZZyqlPuLVQPoF":0,"-L7doomoHmCXdcFXgV2j":0,"-L7dopH3meN_RdPtj6XK":0,"-L7doplJ_bgqf953VbAC":0,"-L7doqFZeK-bhBhTKdCP":0,"-L7doqjnk9hlWNH52fZh":0,"-L7dorE3ZbRemA6RpOE9":0,"-L7doriJZ8iMTVZPEA15":0,"-L7dosCZ_ML46OWPYov5":0,"-L7dosgnO8SQDQR2m8vJ":0,"-L7dotB3ObxUiMfFAncn":0,"-L7dotfI4OmWq5TI1xwX":0,"-L7dou9Zk6ePPKtik9cp":0,"-L7doudoe83qMQIP44Nm":0,"-L7dov83np93jXzDogDu":0,"-L7dovcJjbYv0PuWum5C":0,"-L7dow6Yrdxc7odG-5iW":0,"-L7dowandPP1HjSL-OaD":0,"-L7dox52OTTaTWqwMVTs":0,"-L7dox_IGGkrq7mF4DtW":0,"-L7doy3Y-h_xZfMQwnWI":0,"-L7doyYnHUvP2Ha_rb3n":0,"-L7doz21N3cxDlQKYj7X":0,"-L7dozXI3wbWfAsQxZxy":0,"-L7dp-0YpKqYFKNkmi22":0,"-L7dp-VnozG0bSGX3sl7":0,"-L7dp0-2ewN3yqCgCiko":0,"-L7dp0UIGW9jJCMzZMR4":0,"-L7dp0yYkD4r9he-IQKO":0,"-L7dp1SnIsfCZqPzCkID":0,"-L7dp1x1c91dSs8zRoog":0,"-L7dp2RHQWYkKD1JEepr":0,"-L7dp2vYow9gJLlIm5hx":0,"-L7dp3PmfvtITUAGYON3":0,"-L7dp3u1IAdVBpVUTBuC":0,"-L7dp4OHMZ_W2jmcIyVg":0,"-L7dp4sXvOVyznTC1WA7":0,"-L7dp5MmgdstshaIJBXf":0,"-L7dp5r1yj2Wig4Ut56N":0,"-L7dp6LHULbBZ9hPCZht":0,"-L7dp6pXaTuRDK3yt1Pn":0,"-L7dp7JmQWNEcXBK51VX":0,"-L7dp7o1qZA-5dK5RcaX":0,"-L7dp8IH7vXz-Fr7FUWq":0,"-L7dp8mXn6NdaisVsPLf":0,"-L7dp9Gmk_2bx3ZYGGJr":0,"-L7dp9l1OtLRly3qjiO3":0,"-L7dpAFGVr2GEOt3I5J1":0,"-L7dpAjWFmqheHarLYoI":0,"-L7dpBDm992kRZKQ6M5G":0,"-L7dpBi09EXOCdfRzlXj":0,"-L7dpCCGHanxIr0wg68F":0,"-L7dpCgW_YNyXSt_Jv8d":0,"-L7dpDAktJHrgSrrzcJn":0,"-L7dpDf0-cfLANYXCGy1":0,"-L7dpE9G0oCorv6Qxj0x":0,"-L7dpEdWBVBzXox4gV10":0,"-L7dpF7lhKWRat9eymKP":0,"-L7dpFc0g_rUb0RJOj5R":0,"-L7dpG6Fj8xTfufZ8Xra":0,"-L7dpGaWcYisn1yIHLjz":0,"-L7dpH4lyyq9EkVk4r0w":0,"-L7dpH_02y52JQAUsLnS":0,"-L7dpI3G5Xl6-hSfzyLa":0,"-L7dpIYV-EKWTYFf-dWO":0,"-L7dpJ1l6cqYzfqFQrGW":0,"-L7dpJX-NNrINm1LZCB6":0,"-L7dpK0Fgr5II_sc_LLL":0,"-L7dpKVVLdXSbUzXQ_hu":0,"-L7dpKzkvxPhFG14hrnM":0,"-L7dpLU-yExu7_JKKmj8":0,"-L7dpLyF0jR8vDgqn_yo":0,"-L7dpMSVqINtWPlGmEij":0,"-L7dpMwkP01YIWL-t209":0,"-L7dpNR-VAF1gGRSlxPr":0,"-L7dpNvFPDZIVPrpyIxx":0,"-L7dpOPVpUoP9EuACueq":0,"-L7dpOtkNnF47-WC03Yd":0,"-L7dpPO-lbQFjLTH6IDN":0,"-L7dpPsF9ih_x-WFTyA-":0,"-L7dpQMVT_MfC7J8F4zD":0,"-L7dpQqjnvu0ZAqLjj90":0,"-L7dpRKzzfq18tU0xrIU":0,"-L7dpRpESkN1bFiAdUfN":0,"-L7dpSJUnLb-gIiK-vRj":0,"-L7dpSnjOAxoUL_DDg7C":0,"-L7dpTHzXnJ5vOfGeN0K":0,"-L7dpTmEI5_ZOTM1PNjI":0,"-L7dpUGUjf9HqpPxGfuA":0,"-L7dpUkjAoPlRLcLG4bf":0,"-L7dpVEziRewhg9iPQ-q":0,"-L7dpVjE147xeUY_6kde":0,"-L7dpWDUeADt0JSY959e":0,"-L7dpWhj0Bpo8WEF86hs":0,"-L7dpXBzl1PaqCDWMuAX":0,"-L7dpXgEs5r79w5l7wwl":0,"-L7dpYAUXX-UB-WMl0f-":0,"-L7dpYejoVEvcQLH6pkH":0,"-L7dpZ8yVnR6DstM1u5g":0,"-L7dpZdDAZ0vjVwxxlBB":0,"-L7dp_7TP3Hd2h6kOdsi":0,"-L7dp_biS_etB4hkapEn":0,"-L7dpa5xqM-duikJTQPA":0,"-L7dpaaD84ZLE9DGgtYB":0,"-L7dpb4TXtKtZYo5hihx":0,"-L7dpbZisOahUkbstEK-":0,"-L7dpc2ySY4sBnKsIgg2":0,"-L7dpcYDsAO3KORhQzIM":0,"-L7dpd1SfRA67_3M3Q10":0,"-L7dpdWilySifetwgxxv":0,"-L7dpe-yq35e6WBLyPfE":0,"-L7dpeVC6cJ-U9-EX5rz":0,"-L7dpezSJw6hX-xbR_7w":0,"-L7dpfTipkgb3BkKS-lS":0,"-L7dpfxxi46yYmxVcHkd":0,"-L7dpgSCB1VYlfZBEPJ8":0,"-L7dpgwS59tgrlG6QnNP":0,"-L7dphQhsSNEVygVC9L6":0,"-L7dphux_ilBZVnfXqZu":0,"-L7dpiPCkW_cI07RWvLe":0,"-L7dpitSn6BLMx7zmaCf":0,"-L7dpjNhxHxdNvT7x2jR":0,"-L7dpjrxDpQZ3cpqyU-M":0,"-L7dpkMCNwSD4MjmLoiw":0,"-L7dpkqSJqZQL5oltHx1":0,"-L7dplKhVrJ68s6fDv9D":0,"-L7dploxobevT02NTku_":0,"-L7dpmJC3mIJ9lL1rEwz":0,"-L7dpmnSAVOfptbzFEy4":0,"-L7dpnHhzsfbkaVlo5wE":0,"-L7dpnlxTnus4MivwtxU":0,"-L7dpoGCb3oDCq4Nchl7":0,"-L7dpokRvj5lC-jgqjVT":0,"-L7dppEgmCNl3EHWGmXu":0,"-L7dppiwmYIdKw8ccsLG":0,"-L7dpqDCLY4Na0Ui0wuH":0,"-L7dpqhRoEBLHg94X0eJ":0,"-L7dprBgepKBw_Ar7aPd":0,"-L7dprfwzunRuODakiJA":0,"-L7dpsABuhxIdfZSJ6Zq":0,"-L7dpseRzvNFOsJoZXJR":0,"-L7dpt8gM2CWl4j-tlFI":0,"-L7dptcwLGGcJCBiHzp8":0,"-L7dpu7BvWkeT5nxuukn":0,"-L7dpubRy5uvtaIZZAuM":0,"-L7dpv5fa5xr8yhCbhB-":0,"-L7dpv_wxlw224j0C4VD":0,"-L7dpw4Bqm2pXrLvEUQK":0,"-L7dpwZR2UaJQPjgwp_q":0,"-L7dpx2fwkIk5EBtcdq7":0,"-L7dpxXwFdSaGdJ9Un-8":0,"-L7dpy1AS2nMp0UullaP":0,"-L7dpyWQsNQh658oDUOg":0,"-L7dpz-fhgp0BL-Ul3PR":0,"-L7dpzUvqecidNI8e0m4":0,"-L7dpzzAJdoGl7PdQVlJ":0,"-L7dq-TRrpZQN5umMAbL":0,"-L7dq-xfnQ5WJHEYgLXo":0,"-L7dq0RuFb0KsrTOhgMp":0,"-L7dq0wAZB0zT3JEi_pR":0,"-L7dq1QQJoMibMVpGPMe":0,"-L7dq1ufm7D0-ttieGsQ":0,"-L7dq2Ovj7B3-Qex_CZd":0,"-L7dq2t91OWpCoZvEJl1":0,"-L7dq3NQERAlOXJDTZx8":0,"-L7dq3rfuGhZ_mc5d-F4":0,"-L7dq4LuYlPHZPyNA4mB":0,"-L7dq4q9kjDHXwOmodhb":0,"-L7dq5KPSZNsczcvqogH":0,"-L7dq5oeqVBfpnq3h7p5":0,"-L7dq6IuA9vmCaq_kw0j":0,"-L7dq6n8F9NaYNGRzPfY":0,"-L7dq7HPOLmK6L7wnzfd":0,"-L7dq7leAqP309Bj-koM":0,"-L7dq8Fu1XQoybndYjC3":0,"-L7dq8k9L5PZzYqQF1hJ":0,"-L7dq9EPWMJ8QvL8qz5Z":0,"-L7dq9ie5YnUv_Ac38R1":0,"-L7dqACt8KE67EwEvBJ5":0,"-L7dqAh82DFV4L5EjVjb":0,"-L7dqBBPqrh7t4WFcA18":0,"-L7dqBfeMH8v7Knh8h6b":0,"-L7dqC9uUxYJ_m-lNDcu":0,"-L7dqCe9c7Qm6hW4s5P6":0,"-L7dqD8OyhhOFZ3lZnbs":0,"-L7dqDcdBoYTi1MRr0id":0,"-L7dqE6tleAydwfDFjqN":0,"-L7dqEb8g4cn3Cww4EDd":0,"-L7dqF5OBKTwwLGeAd_i":0,"-L7dqF_dz37CNADWAK5A":0,"-L7dqG3twQcULZae-cTE":0,"-L7dqGZ8w9r9FLfLh00a":0,"-L7dqH2OJqlAM039JDKW":0,"-L7dqHXdNEM_6N-Y834V":0,"-L7dqI0tz314KLfqRRJb":0,"-L7dqIW8tHVq2wFhbAcV":0,"-L7dqJ-OpKoGI3-HFQrh":0,"-L7dqJUdczVLVaX6Fb4q":0,"-L7dqJystGVeAfIa-gRK":0,"-L7dqKT81ESp2XVYN73N":0,"-L7dqKxNNaBNGcA1cpcb":0,"-L7dqLRdJ6jyIItCNOyh":0,"-L7dqLvspY8dbs9ppDfH":0,"-L7dqMQ7BJsZ_BQyGPPp":0,"-L7dqMuNmQQZoaDp8CT2":0,"-L7dqNOcjE9Wnh6bVkME":0,"-L7dqNsselrhtvnconD-":0,"-L7dqON7qZTMtfPQJlnC":0,"-L7dqOrN-r59nj4jebUW":0,"-L7dqPLcufixuGpueTOo":0,"-L7dqPpsTxd8izuuIEjk":0,"-L7dqQK7TDSoH2Sh9188":0,"-L7dqQoNszOzV1Qx-r_I":0,"-L7dqRIcQ_uskLoL8dd2":0,"-L7dqRmrlGbpq0gMw4Qk":0,"-L7dqSH7upigjrneP1Hn":0,"-L7dqSlNOtSJ5f3YrPIT":0,"-L7dqTFbZSLf5BpJxAPx":0,"-L7dqTjrxreXSTB52S9A":0,"-L7dqUE6TlXetXnQkEaS":0,"-L7dqUiMoFJYeMNpRHM6":0,"-L7dqVCb3r7alP6B_6Sz":0,"-L7dqVgrJHdb14lFgXJT":0,"-L7dqWB6sMr8fsJezZE6":0,"-L7dqWfMFRtf80dKnoWz":0,"-L7dqX9buiRv7A8jmkYd":0,"-L7dqXdrOkQQDR-tNXZY":0,"-L7dqY86rgkc60hj3QPd":0,"-L7dqYcMpWXuod3d-ErP":0,"-L7dqZ6bJ1HYED2FOA8h":0,"-L7dqZartYgMNWVivCKC":0,"-L7dq_55GmjD4p2oWcjx":0,"-L7dq__LKXzJ2UxIKemZ":0,"-L7dqa3aoshvCxXK9_uk":0,"-L7dqaYrKJx7va4PKt6b":0,"-L7dqb25PSA6Pbiu74Op":0,"-L7dqbXL53_HvGgYzwEp":0,"-L7dqc0aFOHQallj0Py7":0,"-L7dqcVrnwW5KgiVROL1":0,"-L7dqd-5_FiZFgYP656I":0,"-L7dqdULWo7FsB-92QCO":0,"-L7dqdyagLD0tn_-W5iO":0,"-L7dqeSq7Eq1sREsGmLx":0,"-L7dqex5levLj5pqifIs":0,"-L7dqfRL86YSUIvzAJcX":0,"-L7dqfva7sLZH2gcywo8":0,"-L7dqgPqtDIijD0Tn5wd":0,"-L7dqgu4bCXpQzErcIFt":0,"-L7dqhOLEQ7tzEzis-b4":0,"-L7dqhs_LVF6byWmso8S":0,"-L7dqiMpDNM0FJ8kiFXh":0,"-L7dqir4LSZnowNj_7TR":0,"-L7dqjLLviXiD_ak5qa-":0,"-L7dqjp_3oXZiW0BPVpv":0,"-L7dqkJp8M_0SGlASjjd":0,"-L7dqko4hJGWumlZnp_C":0,"-L7dqlIK-Idw29N6xxAY":0,"-L7dqlmZCAScIRZdHqDB":0,"-L7dqmGpanqNvbz3tVyH":0,"-L7dqml4m36luRvIJq0d":0,"-L7dqnFJMQYRASUmjp_0":0,"-L7dqnj_wjIBTFNgS8eq":0,"-L7dqoDpS2THHMslkW1r":0,"-L7dqoi3WVJuPZqI6sTe":0,"-L7dqpCJgpLlthM73s4e":0,"-L7dqpg_qmmnQIAlf-CH":0,"-L7dqqAoG_b3fwHCUaC0":0,"-L7dqqf3ZuULPklY4G7I":0,"-L7dqr9JI5dLUEFX03vu":0,"-L7dqrd_yD4kK6wzgIkA":0,"-L7dqs7pTBq1me1mH0EG":0,"-L7dqsc3XYevQ-ihwv0h":0,"-L7dqt6JVWRZsvGbBd2N":0,"-L7dqtaZpahUmHr8TPTJ":0,"-L7dqu4ohb8W0DBkPY5t":0,"-L7dqu_3COklF-PQDJDv":0,"-L7dqv3J3LCJm4AyTSrR":0,"-L7dqvYZ9rHagbo3O1V_":0,"-L7dqw1o_s4oh-pkSdiD":0,"-L7dqwX3BXsOv6_MEeAw":0,"-L7dqx0IvTMlXls1BMw0":0,"-L7dqxVZ9YzVyT707gHx":0,"-L7dqxzoBvr_B0JTBYfT":0,"-L7dqyU2NtdEJ0xt0cRB":0,"-L7dqyyIj3IA5dgtEKP0":0,"-L7dqzSZN912TPp8NqNN":0,"-L7dqzwnfDa4EeQZqtXR":0,"-L7dr-R2vVcsEUMeMC_A":0,"-L7dr-vIsm7u8ebXuMpO":0,"-L7dr0PYznZ-XtBn-DZE":0,"-L7dr0tnDVyKiUj8YqwD":0,"-L7dr1O2bSJPC08O9ktc":0,"-L7dr1sImxQSiGxJYQmp":0,"-L7dr2MYFCfkKLRdICs3":0,"-L7dr2qn_6YdGXpnmEx0":0,"-L7dr3L2GNuGWIpY70fZ":0,"-L7dr3pIh3FFOPHkSag-":0,"-L7dr4JXIFd5ogZdNquz":0,"-L7dr4nncMaJbMNcoIPn":0,"-L7dr5I2lAQVce9W8QS7":0,"-L7dr5mICByHTzlVuoRv":0,"-L7dr6GX5ulW-K2Ll_q1":0,"-L7dr6kmpX6dCleJmCfy":0,"-L7dr7F2iLiKpKyBn8pT":0,"-L7dr7jICHxr-eat1sS3":0,"-L7dr8DX_10xB28D8bLc":0,"-L7dr8hm0xaWNSgzyAtr":0,"-L7dr9C16hPQUSZ0isyi":0,"-L7dr9gHOXP4ErsfnkIu":0,"-L7drAAXIo0tOQmJHkS6":0,"-L7drAemo0OETFRYwDH4":0,"-L7drB91W4mNbeC5OD2F":0,"-L7drBdGYbskoiKakXa1":0,"-L7drC7XByUuYA-WqA9d":0,"-L7drCbmWYew8w-VhGgT":0,"-L7drD60F9a-6-Z5GAvF":0,"-L7drDaHQC3S_4qV2ACK":0,"-L7drE4XRNlxKftTIyob":0,"-L7drEZmqklbywOKGP9p":0,"-L7drF30d_MzVC-aJX9O":0,"-L7drFYG9AGyb2e7hc1f":0,"-L7drG1WUyBbNOsiAEG6":0,"-L7drGWlcIaIZ6MNRFyv":0,"-L7drH00IBdvKcp49933":0,"-L7drHVGMN4Cv5eiiz8v":0,"-L7drHzWx_DAp7t1aK4r":0,"-L7drITl3grSRsNYyOoG":0,"-L7drIy0wgT57QKLeDYP":0,"-L7drJSGCyvauwabLJzc":0,"-L7drJwW620d6CPBpRG5":0,"-L7drKQkaUazBerMyImP":0,"-L7drKv-h7xm9aTrVQ-H":0,"-L7drLPFuC9lCr3XZ7xE":0,"-L7drLtW95uDcbhhctLt":0}