{"-L7iityQh5o4HRNJyYhx":0,"-L7iiuSfQE_MEFLVF5Oc":0,"-L7iiuwvuPUUk5pf3n6F":0,"-L7iivRANTUty95hCHYP":0,"-L7iivvQa_3AmWlsVzN-":0,"-L7iiwPfKlRcbLKxLKth":0,"-L7iiwtvRppNPBwkPtQi":0,"-L7iixOAppQ1V0eQm8x7":0,"-L7iixsQ2Xq40rNYeZYP":0,"-L7iiyMfuQMxKbxCpeWq":0,"-L7iiyquJkNRyW4qEeGF":0,"-L7iizLARUvIBzgE8pPL":0,"-L7iizpQRL2bFiCESjqe":0,"-L7ij-JfOhOX0b_IwWhW":0,"-L7ij-nvbwgqrNh3dY-E":0,"-L7ij0I9GPxbPDwBXJFn":0,"-L7ij0mPW6bYDHjCcXGv":0,"-L7ij1GenMSJWKJTs4-b":0,"-L7ij1kuzGPk2MhNPn9x":0,"-L7ij2F9uEXTO_sVImsx":0,"-L7ij2jP-NdLtEUnKtiD":0,"-L7ij3Df1Y1nVJjTxZgK":0,"-L7ij3hz-6IQMcs98b9W":0,"-L7ij4C9upOcFAIggD80":0,"-L7ij4gPL5Uh_NYMTShh":0,"-L7ij5Aefc8lqs8VJFge":0,"-L7ij5eujIugMR1XPDO1":0,"-L7ij699yYihTeknvr81":0,"-L7ij6dP3IQHTQ0--So9":0,"-L7ij77eOl5rnJlV_rJu":0,"-L7ij7buRwbNDICYGaZB":0,"-L7ij8693BddqeT-_5da":0,"-L7ij8aPoXf2DD76w1o8":0,"-L7ij94eJMb2Zdoa28Fg":0,"-L7ij9ZtMRMudvcbobah":0,"-L7ijA38YVe1fIzt10vP":0,"-L7ijAYO-chc8cWFhQCn":0,"-L7ijB1dDsKEIV0qzdaj":0,"-L7ijBWtdCSJL7_ml8A7":0,"-L7ijC08fUuTiZvgL8sg":0,"-L7ijCVOsb01k0FjSZpY":0,"-L7ijCzdqc6npEk1-KdM":0,"-L7ijDTtKE7XQJPR6mka":0,"-L7ijDy7fnCXS9ROhdXd":0,"-L7ijESOlZ8u-zPRGXk2":0,"-L7ijEwcKKSRW6e5qMAn":0,"-L7ijFQtXyV1zkCQOAIy":0,"-L7ijFv8fV2r9U41GGlo":0,"-L7ijGPO5CPgyUBh7Cp7":0,"-L7ijGtdb05ZSpMdCGvV":0,"-L7ijHNtJFN7uoTgsqF_":0,"-L7ijHs8499ELMWc63rg":0,"-L7ijIMNurmiDGvxDk3o":0,"-L7ijIqc8Z7rL8V6MGIT":0,"-L7ijJKsIxfL_is0he6J":0,"-L7ijJp7dw4JJitpZWnz":0,"-L7ijKJNsSGa0pNxBpqF":0,"-L7ijKnch8R6jX_CQWZc":0,"-L7ijLHsD41OACCFQaGT":0,"-L7ijLm78L9cKIsR7l7i":0,"-L7ijMGNzr1jK9cCmfcC":0,"-L7ijMkce77WGlL84ou7":0,"-L7ijNEsmvmKlE3tY1xN":0,"-L7ijNj7r01dajpC7quB":0,"-L7ijODNOc7jXKGW-ZHj":0,"-L7ijOhcHF2A2fkQsl9a":0,"-L7ijPBs-SOxbEHPVxGy":0,"-L7ijPg7buPvx0KIFsJJ":0,"-L7ijQAN9eBQAvHeloyy":0,"-L7ijQecnGWWom3bqxRy":0,"-L7ijR8rtBjRfloQZcXx":0,"-L7ijRd6nqqP-w6hECq8":0,"-L7ijS7MpJePAlspkPkm":0,"-L7ijSbbaOtcdxnIZc5q":0,"-L7ijT5sw_ma0YDV825B":0,"-L7ijTa6Kpf45AhP_b2G":0,"-L7ijU4LBo_h3buoJGGe":0,"-L7ijUZbaOyn35yKmBPs":0,"-L7ijV2rhf4ipfKp7mBl":0,"-L7ijVY6DLDVXFWgm_mn":0,"-L7ijW1MqBedX8iqjo0J":0,"-L7ijWWbT43qejxMVk1e":0,"-L7ijX-r83boPKGChc7o":0,"-L7ijXV6qmW95xRppMlu":0,"-L7ijXzMg2pQccYbRVH5":0,"-L7ijYTbN7onADpwgMs2":0,"-L7ijYxrdVmsONazIhoY":0,"-L7ijZS5DXPRzfxSHFpo":0,"-L7ijZwL0kkuTcoKSotN":0,"-L7ij_QavRJRICB_vQkO":0,"-L7ij_urTqvmtA-lsPOM":0,"-L7ijaP53ooVJf_ELMQm":0,"-L7ijatMkiuY1zPGX_Rw":0,"-L7ijbNa_h3IAvHZiZzX":0,"-L7ijbrqf2rWU9RvKLaW":0,"-L7ijcM5lc5H3siQdwBd":0,"-L7ijcqLG4_Bzuo6GIxw":0,"-L7ijdKaA6zH6laoWGby":0,"-L7ijdoplrW8_4XERyEb":0,"-L7ijeJ57jtj_vc-zspF":0,"-L7ijenLntIAg7oVeOwT":0,"-L7ijfHabS8ZoL4_c12w":0,"-L7ijflqBCFP-ROoOCm4":0,"-L7ijgG6G2dlCGXOL6V2":0,"-L7ijgkLfsLZb25JC3jw":0,"-L7ijhEaP0VkoxEcTeCX":0,"-L7ijhip6Z6G3rpaxRhJ":0,"-L7ijiD5rLVs_IdDtcdU":0,"-L7ijihKDMNq7elvRTo3":0,"-L7ijjB_1clIhkzxWqvG":0,"-L7ijjfptl1_FWfBiEk3":0,"-L7ijkA47MYsu8OF-Ofn":0,"-L7ijkeK-0055WmRhMIc":0,"-L7ijl8_hohyb-4kfXxv":0,"-L7ijlcp0i67lQMjW8j7":0,"-L7ijm74gZ1n7BPUM8AV":0,"-L7ijmbKGLwHwLQ3L5Mx":0,"-L7ijn5ZycvLYpWeDTRP":0,"-L7ijn_p9a287PWa5LCm":0,"-L7ijo44XK7YFOEjsCtK":0,"-L7ijoZKvGqeMNCNOUSw":0,"-L7ijp2_bN20FB41lpe9":0,"-L7ijpXprSxJ7r6UP6Qy":0,"-L7ijq14WKUWHif9jWDc":0,"-L7ijqWJV3DZRQ8XH6gD":0,"-L7ijr-ZvtZhbj2scopk":0,"-L7ijrUoN3J8hagegbZ-":0,"-L7ijrz3r213XFaC7vk6":0,"-L7ijsTJOGeG3DvmtKef":0,"-L7ijsxZEB6CYnSbGbAn":0,"-L7ijtRoYIQt4i6mnKjf":0,"-L7ijtw38_1dvTkrj9hm":0,"-L7ijuQJzPgFYZ4bI6Jx":0,"-L7ijuuZLS1dfa2kHBG5":0,"-L7ijvOod0HPjqkLTb08":0,"-L7ijvt35lwrvbVnrd7U":0,"-L7ijwNJ2rYQs8Qont_V":0,"-L7ijwrZrlfWTGT-XCs1":0,"-L7ijxLoiYt5eaKfGqwG":0,"-L7ijxq37_5HkKuoszUj":0,"-L7ijyKJv-t4kVtsV3Pl":0,"-L7ijyoYkvVr1y23dqEv":0,"-L7ijzInrDFfElGsWlZd":0,"-L7ijzn2LoKz8DIpmKTj":0,"-L7ik-HI38H6ZjDWd3LR":0,"-L7ik-lY1AiFm9pU75Yn":0,"-L7ik0FnOH5mVxFdDBON":0,"-L7ik0k2qseDkZLfCd_K":0,"-L7ik1EIQzCfXgW2x4Sp":0,"-L7ik1iYqgKEJFqrrKT9":0,"-L7ik2CnyeVX_IxlT8bM":0,"-L7ik2h2cBooUrxQb0gV":0,"-L7ik3BIWxUPotMQVwHg":0,"-L7ik3fYOLf3jlugSj95":0,"-L7ik49n8-dYfqeLStvO":0,"-L7ik4e2XScppFHpBL3b":0,"-L7ik58HwAeXf_ICyLjS":0,"-L7ik5cYLgHSvP2SBQXD":0,"-L7ik66nqEhTF-FZhGP5":0,"-L7ik6b1RFU8xecoFmFH":0,"-L7ik75IM6YgSoXPUMEP":0,"-L7ik7_YBHsj_Ka0NL-6":0,"-L7ik83nFvO8r1VUzsdh":0,"-L7ik8Z1vuzlj0u6QT1n":0,"-L7ik92Hjnm2iQ80X4Gx":0,"-L7ik9XXq7y2r54P4pKz":0,"-L7ikA0m899sDT-fVtv2":0,"-L7ikAW1uAFkQGFCn5vi":0,"-L7ikB-HqlxvdcbA28YY":0,"-L7ikBUX3jeuAsgEd4WV":0,"-L7ikBymVKZ32wW-tgkR":0,"-L7ikCT1hy6uUI7yw6iY":0,"-L7ikCxHWwAvoLsys6F6":0,"-L7ikDRXCajgXmZ5KLwJ":0,"-L7ikDvm8cjHPXaMKIv-":0,"-L7ikEQ1E36u8PF1cnF4":0,"-L7ikEuGDnGMjhJTHKY1":0,"-L7ikFO_e81ICA8B4kLx":0,"-L7ikFsuoollU7ETEb3e":0,"-L7ikGNBl1Bg9X8bKQ-m":0,"-L7ikGrV3Kp895NKbn-T":0,"-L7ikHLnh_GsflL5iK52":0,"-L7ikHq419Nv3mhr0-e3":0,"-L7ikIKMDcNllEUh5e_V":0,"-L7ikIodThr6emWocKCB":0,"-L7ikJIuArRiS7EguKPR":0,"-L7ikJnB900qSTHv-ln-":0,"-L7ikKHSy_8doFzIASqd":0,"-L7ikKliBU_PrgPTONKp":0,"-L7ikLFz0yigjaGli6BC":0,"-L7ikLkFpuPLtatZwsM-":0,"-L7ikMEWI4l-HeQlt_tG":0,"-L7ikMilPrLRi-ekQXXJ":0,"-L7ikND1LVQ_YUSmORMd":0,"-L7ikNhHwsAjApLq9y_m":0,"-L7ikOBYmXD3ocFdkgc8":0,"-L7ikOfnZDKpDTgcDOOh":0,"-L7ikPA3C9V9DgwSai6n":0,"-L7ikPeJ9THhk7G0eSWZ":0,"-L7ikQ8ZHk1ipAB1aji4":0,"-L7ikQcoZu7oejxsWs29":0,"-L7ikR73SVbNI2aFYe1M":0,"-L7ikRbJ4WDDTzjLUSrP":0,"-L7ikS5_8cRGBahf_W_U":0,"-L7ikS_p4pM4WgMfgO_g":0,"-L7ikT44EvklaXATNsAg":0,"-L7ikTZKx2seY_2RZFCd":0,"-L7ikU2_cQt6DeH2D0gO":0,"-L7ikUXpERubL9GyABY2":0,"-L7ikV14VPOPKPJZt9TE":0,"-L7ikVWKFOaLFLwwA0dm":0,"-L7ikW-_lChF0pvnDkPW":0,"-L7ikWUp0dfZY6MLvd31":0,"-L7ikWz4TydShfRtrhlp":0,"-L7ikXTK0tIbt7a6DKux":0,"-L7ikXx__lGZiMDNmrCM":0,"-L7ikYRpMIHbdrPtD6d7":0,"-L7ikYw4XiA6uDpwbRsb":0,"-L7ikZQKZ7G4MSrNAjH_":0,"-L7ikZuZpTEiLO6pc0Qc":0,"-L7ik_OpZgyHBnashqHK":0,"-L7ik_t3gpTSd_ECb9W1":0,"-L7ikaNK1HYyP3y_8kvF":0,"-L7ikar_WO2vKe79uAzF":0,"-L7ikbLolyGLKcvMbgzh":0,"-L7ikbq4RU-X1xGmYXVP":0,"-L7ikcKJda-RccY_v46V":0,"-L7ikcoZkNQaDdJHV6Xs":0,"-L7ikdIotG4jMb6igrAN":0,"-L7ikdn3-T-b8RawG0UJ":0,"-L7ikeHIAoI4Exl0dDQX":0,"-L7ikelZIfTleeYtyvMD":0,"-L7ikfFohRsF_kg94_-8":0,"-L7ikfk3G_qaR2r0GcJ0":0,"-L7ikgEJk_3qJSsl4tk4":0,"-L7ikgiZRrKu9r7HGpCn":0,"-L7ikhCoAHqwIJtmf_Jd":0,"-L7ikhh3jPKvyljV3YZL":0,"-L7ikiBJGCkqrWynAcfy":0,"-L7ikifZhizwBK52V4B7":0,"-L7ikj9oZY516ngArKbc":0,"-L7ikje3Dpm7IoiwTxgH":0,"-L7ikk8ICvtcqBPHtexi":0,"-L7ikkcZwJhnoPBK5d_C":0,"-L7ikl6n-sDfWmg8qnz0":0,"-L7iklb39totE5F2M97T":0,"-L7ikm5IPEurdyU5FQ6c":0,"-L7ikm_YDHN0fmDEcbaC":0,"-L7ikn3n9MbHpzEnWVP8":0,"-L7iknZ2WpbHXFeSfbba":0,"-L7iko2Ju8t6fzCZDk2M":0,"-L7ikoXYLJbpUdrLPMFA":0,"-L7ikp0ngKyRlf8tNOI_":0,"-L7ikpW21HQIlrdmogcM":0,"-L7ikq-I0z_ietqtC9-3":0,"-L7ikqUYE5qdEvjace8T":0,"-L7ikqynm80pE5Y1NmZ3":0,"-L7ikrT2VVtE4_VeRJTm":0,"-L7ikrxHzY00mQuue36-":0,"-L7iksRYJMBvuNJAWVk3":0,"-L7iksvotreO-w_ynNTH":0,"-L7iktQ2bsFSJo7EpyLe":0,"-L7iktuHjXvV6-f4E2Gy":0,"-L7ikuOXLqN_tNPtYo85":0,"-L7ikusmSTICyp92aHN4":0,"-L7ikvN1OQeN8uw9yOcf":0,"-L7ikvrH-IALOpmcMrIs":0,"-L7ikwLX_GFwCXRjbE0R":0,"-L7ikwpmbYQeHty4MpHo":0,"-L7ikxK18nw68Q_F-CAi":0,"-L7ikxoH6Ck8EcT7ntB6":0,"-L7ikyIX8wyZLyMR6aib":0,"-L7ikymm54nMJlF06D5-":0,"-L7ikzH1U6D7bhUz4bor":0,"-L7ikzlHoAKwKy_j6S0Z":0,"-L7il-FWH6viFf7QPs6K":0,"-L7il-jmw-WYSmQzcLFI":0,"-L7il0E1RRovZgoP3jO8":0,"-L7il0iHkLQKjY0gIXBU":0,"-L7il1CWd-CfxJLdT90K":0,"-L7il1gmaMqZUqOAIqoJ":0,"-L7il2B0sPbf-r9TQtFf":0,"-L7il2fG9Gfx8RLAEed8":0,"-L7il39WDULS-hmBHMG6":0,"-L7il3dl30Ka8-A1BjPT":0,"-L7il480k2gqoWjCfGip":0,"-L7il4cGgJILyPKetymd":0,"-L7il56WR2hBBb-AudtX":0,"-L7il5alWAKaHpfGE10_":0,"-L7il650DAqwq6hBA5Zi":0,"-L7il6_GJubNhW_Svlvi":0,"-L7il73W_3XikGm_PcIM":0,"-L7il7Ylfoz5z70sMdQm":0,"-L7il820D-w_x3DEzWJc":0,"-L7il8XG9PxqqBSokBEh":0,"-L7il90W_taavADpMfZj":0,"-L7il9VlSBayd-GjTd1U":0,"-L7ilA-0fgEpjxDdJTGI":0,"-L7ilAUFLb-wsLSL9O2E":0,"-L7ilAyVlPiQQuc22Fwu":0,"-L7ilBSk82NRkKRU4BDI":0,"-L7ilBx-nGDcpJrKJN9F":0,"-L7ilCRFBaMUQ--JBqt1":0,"-L7ilCvVpI5pmFt87xDq":0,"-L7ilDPkEqFQU7xumMc3":0,"-L7ilDu-G90etdyACoYy":0,"-L7ilEOF7remyoZgXXTI":0,"-L7ilEsV6gHgz0ngyBdH":0,"-L7ilFMjYrzC28vnXNEa":0,"-L7ilFr-_VHCR3veUWmV":0,"-L7ilGLEUmkJKEV3mnYM":0,"-L7ilGpVhlGIbYG6tGIq":0,"-L7ilHJjrqGCgGpOzI-Q":0,"-L7ilHo-N0NSmlE-ImLP":0,"-L7ilIIFIxZsVNOittYd":0,"-L7ilImVGBzFyKrxoZJU":0,"-L7ilJGjmQ8YkNpeBDIE":0,"-L7ilJkzyxsh3ukH17y2":0,"-L7ilKFELS5PrJglQE1s":0,"-L7ilKjUYaEgeYb8tv78":0,"-L7ilLDjad3UBv9WAzMt":0,"-L7ilLhzpNhGes6NFYXE":0,"-L7ilMCEmBeMt10qjOkO":0,"-L7ilMgUm3XfmKvAJQnf":0,"-L7ilNAjFAWCrV-ODkqQ":0,"-L7ilNezfotXQnulm5xO":0,"-L7ilO9E8PB57gqtK77o":0,"-L7ilOdUktsBkVmfIsgI":0,"-L7ilP7im-mBlJmcNIGG":0,"-L7ilPbz7mofTY5NHo4r":0,"-L7ilQ6ELcyhQLjXYKyG":0,"-L7ilQaUIFk8fW0_Vl_-":0,"-L7ilR4iEFacgAIWR9iL":0,"-L7ilRZzhVUgO67_3lb-":0,"-L7ilS3DX0sYAFLXddwo":0,"-L7ilSYT3FWNn63x27r7":0,"-L7ilT1i-dx6uH-iun2E":0,"-L7ilTWykxLpnlcTuF1P":0,"-L7ilU0DErsltSWuREWY":0,"-L7ilUVTgpeMRJeBH4x6":0,"-L7ilUziTN0xgCAMFk37":0,"-L7ilVTyhblP-nMXsIPC":0,"-L7ilVyDtS0zakKuovca":0,"-L7ilWSTcjnTRQLiTT0_":0,"-L7ilWwiO7RAZ2BoCO2z":0,"-L7ilXQyIXC22CBYeDKQ":0,"-L7ilXvDtZh0EBseq-GM":0,"-L7ilYPThwpb678mrkYF":0,"-L7ilYtiZ9CpFBFeJ7-i":0,"-L7ilZNyISwewntRbqMJ":0,"-L7ilZsD71b0iOVfuDJr":0,"-L7il_MSF8Q84eXlrJtu":0,"-L7il_qh8ljoy4z2RxS8":0,"-L7ilaKxK2_y6Xrs6eHO":0,"-L7ilapCarViqfYCvrsK":0,"-L7ilbJSBksSpLnHMYEc":0,"-L7ilbnhkRHoGL8ttRpr":0,"-L7ilcHx-BejtDJRREH1":0,"-L7ilcmCzmb1LYvQucF-":0,"-L7ildGS3ob5gAz9lXCR":0,"-L7ildkh8k8FLiqFp6Yk":0,"-L7ileExF1IWQ6EjaNV6":0,"-L7ilejCRUvhvVA16DlI":0,"-L7ilfDSHHMcJ7ftvRgQ":0,"-L7ilfhhRvjEbHxFUKYe":0,"-L7ilgBxZLVb4ob7vPEC":0,"-L7ilggCXIGjPuNS3mCZ":0,"-L7ilhASeXCO1V0jgKEf":0,"-L7ilhegBjhxbkRK5C0J":0,"-L7ili8wcNyYF0nj67f5":0,"-L7ilidBTDHrzbmlDUvX":0,"-L7ilj7RPicrFjTtD-ab":0,"-L7iljbhhaa3XpbcE5K9":0,"-L7ilk5w_pzMG8YD4_aa":0,"-L7ilkaBuNQDK9RO6z3I":0,"-L7ill4RvGQOBz1eWC5m":0,"-L7illZgw3J6y5_8de8s":0,"-L7ilm2vongRKL4UOuFI":0,"-L7ilmYBZWL-W4ky_vNo":0,"-L7iln1RnE01l_ORFYH4":0,"-L7ilnWgY3l5dKu7dWCX":0,"-L7ilo-wjs-Hpt4Mc0_f":0,"-L7iloVBxhzDiX-hLbSO":0,"-L7ilozRWxZw3RFz0skK":0,"-L7ilpTg6zzOP73UwU45":0,"-L7ilpxw-AeMkCIhO99v":0,"-L7ilqSA4XjxJQQ9ni_5":0,"-L7ilqwQAf2ezWkBXUjU":0,"-L7ilrQfwy8cacBaV-JY":0,"-L7ilruv4xBFKO7EG7_A":0,"-L7ilsPARqyZKPN4z5Zm":0,"-L7ilstQvENhkHDs7HF8":0,"-L7iltNfkvPmikETzOaV":0,"-L7iltrvuHi-qPeOaU2X":0,"-L7iluMAtLDcG7-T9-lc":0,"-L7im-D9Kgu9jZ3yqQLt":0,"-L7im-hPDI4sE6BN6Agi":0,"-L7im0Be9wadNFzELrxb":0,"-L7im0fuJjK2omId_j4Q":0,"-L7im1A9HlG92G_jTzYl":0,"-L7im1eP1IiUy_gW_pi7":0,"-L7im28eH4QI8tZ5vbjQ":0,"-L7im2cuJm2kDCn08KM_":0,"-L7im3790biVaQs42Umm":0,"-L7im3bP8dtZKBvxpMp4":0,"-L7im45eXY2nZTGpVOcz":0,"-L7im4_uj8kY4NzFNHrw":0,"-L7im549gYMLoWGFbpML":0,"-L7im5ZPn1qWXBY7m4mR":0,"-L7im62eTAkiMbCnS9-J":0,"-L7im6XuI0n4H9QEudyi":0,"-L7im718BAs7T6gMY4NO":0,"-L7im7WOxzKbKcCteJMi":0,"-L7im8-d4gCr2AqoJfMP":0,"-L7im8Ut94r3idEXJTeX":0,"-L7im8z8xlojLw85b1PQ":0,"-L7im9TOYvFUD7Ut_PSs":0,"-L7im9xd7wOwqCGia_5p":0,"-L7imARtPry7K7OyojO5":0,"-L7imAw8euU9R69xRDJQ":0,"-L7imBQOeimE0-lcWlbI":0,"-L7imBuduUv1c9lgZzsB":0,"-L7imCOtbJYpVXvJvWcP":0,"-L7imCt8wJeYuml_Nmcv":0,"-L7imDNOaDgnYTH1tXdR":0,"-L7imDrdIKwhSl6DXeyd":0,"-L7imELt27qMLXF3h3JW":0,"-L7imEq8cFwWDel9BjHP":0,"-L7imFKNlxZG0ZxbAekI":0,"-L7imFocc77Ng2i0p-QD":0,"-L7imGItWt3YUw9xa65d":0,"-L7imGn7d5MlAob8yHUW":0,"-L7imHHNetuhu0A1Awiv":0,"-L7imHlcO7NJhCbwj1Aw":0,"-L7imIFsVC2CLLUHJtTp":0,"-L7imIk7_0-44yteSICE":0,"-L7imJENN72BMDOiA3Ex":0,"-L7imJicL0O603_SB0X8":0,"-L7imKCsD-pJuDye0mo8":0,"-L7imKh7rSkezmwLitpr":0,"-L7imLBN7dlDmqsUvxrQ":0,"-L7imLfcxnnmttt5X31f":0,"-L7imM9sb8CDIco70Xlk":0,"-L7imMe7hvElo9j7A0Q1":0,"-L7imN8NxS8FjJL5ynAa":0,"-L7imNccFLenF-oCoKbq":0,"-L7imO6rYBgg5U-XI88D":0,"-L7imOb7pnErOz5cxYDW":0,"-L7imP5M5GPHFhi9jZe0":0,"-L7imP_bE0rGNlgBMDn4":0,"-L7imQ3rA1pfSU6lm7Mc":0,"-L7imQZ6XVeu6DPvHMVo":0,"-L7imR2Mqe0HLo171vcd":0,"-L7imRXbiGuJIUHByRTN":0,"-L7imS0r4fwymDnOYYti":0,"-L7imSW6xV2QgDDEgURG":0,"-L7imT-M6RyUqGvpq-JT":0,"-L7imTUbPLZKDHaOjcef":0,"-L7imTyrEP8sMtGJK0lp":0,"-L7imUT6l9trpsxthDtd":0,"-L7imUxM_wBZWxn0KEXJ":0,"-L7imVRbr8bhdtuopZnT":0,"-L7imVvrk_q4bxKhTKrZ":0,"-L7imWQ6SuvESXPB9QOT":0,"-L7imWuMP1iIJvHtwTiZ":0,"-L7imXObnegfW2YqY3GT":0,"-L7imXsqDTEIBKlEtygu":0,"-L7imYN5yZwaFEy_Z2jv":0,"-L7imYrLrFnAJxCdADuP":0,"-L7imZLaor7E8eeZdJ7e":0,"-L7imZpqCfwh2d8xty_I":0,"-L7im_K5BsghrdMGrCZE":0,"-L7im_oLDDl36AGCKngk":0,"-L7imaIalc51oosEY4Qw":0,"-L7imamqFKrZimmjj1bK":0,"-L7imbH5dufxM3RR74kX":0,"-L7imblLDRw70Zs4pel5":0,"-L7imcFagL724sHIDSFN":0,"-L7imcjqqG3M6IebphDn":0,"-L7imdE4cQnKKLBEqSTx":0,"-L7imdiLHFi5j8M9R_bA":0,"-L7imeCas-U6GWMwiqSS":0,"-L7imegqreTf5B2CoOgz":0,"-L7imfB4cA5H6V2ZWeng":0,"-L7imffKpmsrMxwa-HdC":0,"-L7img9_wWMR8f2jJeFt":0,"-L7imgdpOXONsGhLWK6x":0,"-L7imh84pUmUx4Q_YyG1":0,"-L7imhcKiMkGq6WRMLTt":0,"-L7imi6_PfDncm0h7x1-":0,"-L7imiap-RiW1fYsVBiU":0,"-L7imj5460w0eRNn3xFV":0,"-L7imj_KpmhmxdvPbOuq":0,"-L7imk3_XTQ45zzdl1St":0,"-L7imkYpb3a0e3WPA-AW":0,"-L7iml24cmcQTXZW0sVG":0,"-L7imlXKSNFWJgwNCXWb":0,"-L7imm0_8UuaT_vBx5jc":0,"-L7immVpgDRtI3BW8ypD":0,"-L7imn-4H589Fzt6DpgH":0,"-L7imnUK5rSDjbv6eFK6":0,"-L7imnybQxN3Pk-RYtES":0,"-L7imoSosepVIR_5TNFf":0,"-L7imox3htZWKmW1H19I":0,"-L7impRJltbK0FoHyPTN":0,"-L7impvZmxjwf3pukdI8":0,"-L7imqPoYHofMg0x0GR7":0,"-L7imqu34OZTafTwD_xC":0,"-L7imrOJS1LDfawkhfXz":0,"-L7imrsZA24yLLB9JVqP":0,"-L7imsMokpbRmbh1msOK":0,"-L7imsr30RRYdM-7OmN1":0,"-L7imtLIT951OeTcDbWl":0,"-L7imtpZOjll6wWbc4Ge":0,"-L7imuJoullHMKNrF-8O":0,"-L7imuo3BI2dUeYrV5SJ":0,"-L7imviXZWC7QFEXGl2l":0,"-L7imvmY1atVufE8vpfa":0,"-L7imwGhqc4TKWqONlO8":0,"-L7imwky0_ZJKooEKTNd":0,"-L7imxFCCACAvwSIbHHi":0,"-L7imxjSQ-mzHfEf0FnJ":0,"-L7imyDhme8wM01BrggI":0,"-L7imyhxZ_A9h3-Xooh7":0,"-L7imzCChe8wEkYRokZg":0,"-L7imzgSVrjtmiOxRXcc":0,"-L7in-AhutG5K3_9MMXc":0,"-L7in-ex6TGPDi4AVGf0":0,"-L7in09BZFkIzbn2r1Ej":0,"-L7in0dRCqsMjAEL7qV0":0,"-L7in17gwAyTz3dKPcGM":0,"-L7in1bxnghVM3iKpL-8":0,"-L7in26CvmjbisNJCex1":0,"-L7in2aSK68h4KJGP3yK":0,"-L7in34h2GWH2s6v874g":0,"-L7in3ZwRR21axlajrAy":0,"-L7in43BN8V1agVlN6JO":0,"-L7in4YRdSoJPvdbki0n":0,"-L7in51gpiuc4ZeYZwh6":0,"-L7in5Ww-63CydJU9Jdp":0,"-L7in60Bh57J8_3-wqRj":0,"-L7in6VRvcWUJZfCsy0U":0,"-L7in6zgc3DDjhdUrTQB":0,"-L7in7Tx9Re6ggCpUyqj":0,"-L7in7yBgjrdDKjX6BXy":0,"-L7in8SRotny2OEGTtBF":0,"-L7in8wgq5gv3_ytueBm":0,"-L7in9QwqKJ0xpHSDTHo":0,"-L7in9vBRf1w4UWQDMkZ":0,"-L7inAPRVN_bJrGdmN9d":0,"-L7inAtgBcdaGYcbxyfW":0,"-L7inBNwwV1EOAc6bXW5":0,"-L7inBsBWyghB1MHsq6o":0,"-L7inCMQ_BqdzROHLDcP":0,"-L7inCqf3oE9DqivpO-j":0,"-L7inDKv6gaqdYSL5rX4":0,"-L7inDpA8igxKE29D3Mr":0,"-L7inEJQpsiHKmBsIoLD":0,"-L7inEnf4P7s3q28YFnd":0,"-L7inFHvok3BA__YK59u":0,"-L7inFmAoHfX3tQ8QnMi":0,"-L7inGGQTZrx-HJ6VOPS":0,"-L7inGkf0qNDTr-A6mJi":0,"-L7inHEv9FfdUrNFfNvz":0,"-L7inHjApRDrKsaOVZTd":0,"-L7inIDQkF2jY7XXDjX4":0,"-L7inIhflq4qs0c8aLP9":0,"-L7inJBvLAJ9CHccZhQ4":0,"-L7inJgA3d58i_jdNieg":0,"-L7inKAQEe7JHdOuADNf":0,"-L7inKef3qfoRRG4Q3CV":0,"-L7inL8uhTyOn8dmr0v0":0,"-L7inLd9OXG_mL0QH6ac":0,"-L7inM7PIy6s2dnS_Sa6":0,"-L7inMbezGfChYn34tnr":0,"-L7inN5utBBVoyeEX8is":0,"-L7inNa9zbHff7qYLF66":0,"-L7inO4PiRxeN_4xBjfB":0,"-L7inOZevZwFL3DhLOw9":0,"-L7inP2uk0vAucn9dL_M":0,"-L7inPY9gavKJQr4ET40":0,"-L7inQ1P7dCvT9KhP3L-":0,"-L7inQWeTGXxuSqV2WiF":0,"-L7inR-un7W-AIKuzfN5":0,"-L7inRV91JBaoKrawlev":0,"-L7inRzPMTUivfwTxwR_":0,"-L7inSTeM_crwxvGPUKT":0,"-L7inSxt9EjPdN1AWV4O":0,"-L7inTS8Cz39zWExjgPC":0,"-L7inTwOtqVtFnpHnEx9":0,"-L7inUQdBccT6f8ftlby":0,"-L7inUutfYcFlb2oY6lU":0,"-L7inVP87z5zc1PGAIZ3":0,"-L7inVtO3CatNf21hk19":0,"-L7inWNdS5Z66_k3BmqI":0,"-L7inWrtTo9FP5zk4lv6":0,"-L7inXM8f5caaC7Wa-6v":0,"-L7inXqO5kpWRm2F-qd1":0,"-L7inYKdJa1CpsTeX-Rj":0,"-L7inYotcovS4wbZFZBW":0,"-L7inZJ8j5TucTzun4og":0,"-L7inZnOz1_b509XccOM":0,"-L7in_HdZCaqAEi0RMmo":0,"-L7in_ltfyDuviaammZ1":0,"-L7inaG85bmkb9Zy1hB-":0,"-L7inakOarKw2OuGyzpN":0,"-L7inbEcvX7INrJF_TEt":0,"-L7inbisieh9pnefGMST":0,"-L7incD7GaWWrZHerOcb":0,"-L7inchNIDpqvxMPnWcv":0,"-L7indBcCR0S8fJYfmEq":0,"-L7indfsLHyT3Vn0o3r9":0,"-L7ineA7Le1u3oLqDGKB":0,"-L7ineeNbvyxQOhK8kVk":0,"-L7inf8cfUUwXU2-iVT2":0,"-L7infcs4x5FWd-2fNgP":0,"-L7ing77XhGv8mtoxLLc":0,"-L7ingbNZB_XTQQ09rG6":0,"-L7inh5cWqEm0dkT0XW4":0,"-L7inh_sRnuKmylE3_xf":0,"-L7ini47wuUeLOQ7PFa9":0,"-L7iniZNxu6myhgeqpVf":0,"-L7inj2ccNnHXZrgVwdZ":0,"-L7injXrB19nfBtzq0FA":0,"-L7ink161xmxGeFs6lQo":0,"-L7inkWMyIXcBA3uuSXO":0,"-L7inl-bNPMRLIY-Jvgt":0,"-L7inlUr28oZVhyQ0ULE":0,"-L7inlz5ZrwiUTuNGKnf":0,"-L7inmTMLKk-cIhsKhyn":0,"-L7inmxbLVzp3WYqK3PU":0,"-L7innRrQ24GB_XR7rRY":0,"-L7innw6hBhZBfczphDW":0,"-L7inoQMbbBRh-mHnavS":0,"-L7inoubLzwysy98a5Yt":0,"-L7inpOrDXrji_mvvwNP":0,"-L7inpt6QP55wHQ6h7-S":0,"-L7inqNMwZlHCv_F21Qg":0,"-L7inqrb3LVmeUEsSNEk":0,"-L7inrLrs0bwGS_DvCLH":0,"-L7inrq5gnzyD-trKFsz":0,"-L7insKMSSFnwO_q5bdT":0,"-L7insobTpmZ1ARG0024":0,"-L7intIrKFtvytmNMrzA":0,"-L7intn56uEXeLqnKsnI":0,"-L7inuHLF0ERr9lD3Ukm":0,"-L7inulaTZbLN94huG49":0,"-L7invFqCn7Qidou-LqC":0,"-L7invk5cAKUEPziJJvT":0,"-L7inwEL1SQVVGkDtzcf":0,"-L7inwiaXbbj_1llmYYz":0,"-L7inxCqUPxJnf9fjK43":0,"-L7inxh5TswcfXI90_Ak":0,"-L7inyBM0704CiMYUqFe":0,"-L7inyfafpywhK9c4V87":0,"-L7inz9qHvqUWA9iLQ_-":0,"-L7inze5rlmeD-Cxz7LG":0,"-L7io-8Luygc_7DD8wlj":0,"-L7io-c_FxOHC8aVfNpu":0,"-L7io06qH3eN27sg0247":0,"-L7io0b4E4fdmj3Pvaq5":0,"-L7io15KCQrHgmmgE5no":0,"-L7io1_aMRKPGgZNwU26":0,"-L7io23pDRamJ05CywIY":0,"-L7io2Z4SW1F1vCDUKUU":0,"-L7io32KBwOFMKwEEAk9":0,"-L7io3XZvljcl1UMK5NK":0,"-L7io40pVBXBK2yeUYt5":0,"-L7io4W4wLpcouaiCavY":0,"-L7io5-K8dbWSrvhkWla":0,"-L7io5U_sgEuSX44ZEQB":0,"-L7io5ypa2t6sXyZf46_":0,"-L7io6T4jzmezM47O8m-":0,"-L7io6xKSc6JybbCanxP":0,"-L7io7RZGzvwTEobCP2r":0,"-L7io7vpBHC0CNuGNf_5":0,"-L7io8Q39zM-n7vKvXFq":0,"-L7io8uJQ6DpJkOVk3em":0,"-L7io9O_svjXkdm6mwR0":0,"-L7io9sol_2c-OU0O7uv":0,"-L7ioAN4Xu6rcl5Ahuun":0,"-L7ioArJbrdU4PYR-7-7":0,"-L7ioBLZ_kF2Mi9sISFq":0,"-L7ioBpopOcYj9KYAxmx":0,"-L7ioCK33jYVjcjuhS5F":0,"-L7ioCoJmmPUfUtFxG8L":0,"-L7ioDIZfuZ4DHMXdS9Z":0,"-L7ioDmoKM3DFCO24Z9_":0,"-L7ioEH3-L6TzWBPpA_8":0,"-L7ioElJi4Nj6Ww9UT9t":0,"-L7ioFFZyXwNNuah6B7l":0,"-L7ioFjoqePxqVkqqGQr":0,"-L7ioGE358F5F8CzZgnz":0,"-L7ioGiIa0iyXqoq6huf":0,"-L7ioHCYvxYt3xHPmBMt":0,"-L7ioHgnA8YknWWXCxhx":0,"-L7ioIB2KjO9FTW59V7J":0,"-L7ioIfIXX61Bs16Nt48":0,"-L7ioJ9YzoXU57DuXkF0":0,"-L7ioJdnAuwhrDlGxgLG":0,"-L7ioK82mK6CH5ubIz7G":0,"-L7ioKcIbxy7GgdDjEsC":0,"-L7ioL6YA5JoyeqovqPC":0,"-L7ioLan-TzkZpVYmYHW":0,"-L7ioM52TDl_eUmtr16O":0,"-L7ioM_IMOGj9FCh9520":0,"-L7ioN3YvkPtK8RylruG":0,"-L7ioNYnFYPkuh5_Rd_9":0,"-L7ioO22LdFzP-z7DIHx":0,"-L7ioOXIl-o6pnTJWUVy":0,"-L7ioP0Ybhl3bmQTdl_y":0,"-L7ioPVmjoG80nd9cm9J":0,"-L7ioQ-2BWmSSgUNOPzh":0,"-L7ioQUI8uBUWxT4Vfta":0,"-L7ioQyXXIvGX6pINpe5":0,"-L7ioRSmEgkhmkPIrsEF":0,"-L7ioRx1qhq_5zZOIkh5":0,"-L7ioSRHNLg_o95rqs1F":0,"-L7ioSvXjq7B0kyUjpcS":0,"-L7ioTPmztEmweQE65d2":0,"-L7ioTu1-J0PfHNpCGR_":0,"-L7ioUOHp0xVIC6PSHjn":0,"-L7ioUsXZm2NxNxs29kL":0,"-L7ioVMmk4Z01KjNKryt":0,"-L7ioVr18ZKYsG5vN7u9":0,"-L7ioWLHU_XUQel-Vx24":0,"-L7ioWpXJxfgn4vkR1hg":0,"-L7ioXJlCCevOyZgFPhS":0,"-L7ioXo0JrDCESmGzWQl":0,"-L7ioYIGL0Z0yqYLeRJC":0,"-L7ioYmX4CYY8OZgNWmf":0,"-L7ioZGl_CN4EMjGE-ZC":0,"-L7ioZl0YYrpk5_k_6cX":0,"-L7io_FGL6ezENdZm4bL":0,"-L7io_jWie4Ln8m9vxiD":0,"-L7ioaDmsWIGaHHO7A7O":0,"-L7ioai03GFHg9mOsKLm":0,"-L7iobCGf4_Btqt1Plg_":0,"-L7iobgWlWOS2H28_E_6":0,"-L7iocAlONHluQ4Ds3lF":0,"-L7iocf0H7z4xEKdc6Ao":0,"-L7iod9GciGMPameLQ4B":0,"-L7ioddWH-ySwgBpQBhv":0,"-L7ioe7lac47WXPth-b7":0,"-L7ioec-VpSYTrtrwTFd":0,"-L7iof6Gs6e1FCZBrETC":0,"-L7iofaV_o98ufwtRcL4":0,"-L7iog4lkQBGMV5ECnYy":0,"-L7iog_0WWqoDSUh58P0":0,"-L7ioh3F4pf9E7h1Tg_O":0,"-L7iohYVOd-vSpvUTkfb":0,"-L7ioi1k6btIPprE4Ujt":0,"-L7ioiX-6U2e_ToSIbRU":0,"-L7ioj0FDp4sqY6AoYgx":0,"-L7iojVVd9HTzCu5YPRR":0,"-L7iojzlY8pwmhLw9PNn":0,"-L7iokU-IjmRQfMQ5K1j":0,"-L7iokyFPG_J39Ksnx4i":0,"-L7iolSV2ngbbFKiZKca":0,"-L7iolwkNvc2BkjrONBV":0,"-L7iomR-UTyaMvXr9Qbk":0,"-L7iomvEWnubkuNv0-yO":0,"-L7ionPVpEsIRb4hZymk":0,"-L7iontj5H9r7XD39Ja1":0,"-L7iooO-SnybvTbzdNQV":0,"-L7ioosFWSxB6gDxK6Er":0,"-L7iopMVgsYQ0Q2w-hts":0,"-L7iopqja6J5xlMbDnmm":0,"-L7ioqKz5ZBtOuBErB6m":0,"-L7ioqpE4c84mOqrSJwQ":0,"-L7iorJUjSuYgYMuXU6h":0,"-L7iornjczwy4xxUs5Ce":0,"-L7iosHz_TRoV7aW1vbq":0,"-L7iosmEqonserbTxtfW":0,"-L7iotGUW7SKU2Lq2T-W":0,"-L7iotkj_Cr5HWGzGpQZ":0,"-L7iouEzS5gXpykWmuHA":0,"-L7ioujECzulMW7cxoXI":0,"-L7iovDUi53RoJCpUiNE":0,"-L7iovhjua9u3i9kEcRr":0,"-L7iowBzWHEFwSnCaiki":0,"-L7iowgEqKOhV5GEFB-X":0,"-L7ioxAUXZ7aBBDD47D8":0,"-L7ioxej1-n_7PKY2X01":0,"-L7ioy8y0lDORMypvgWN":0,"-L7ioydDYX3H7WO4kk18":0,"-L7ioz7T8ggRQ9ubxCAL":0,"-L7iozbiuUdH8MXHwDig":0,"-L7ip-5y3od4qGSjh2t0":0,"-L7ip-aDyaEfJRf_EUv1":0,"-L7ip04Th81FYCXoOiUf":0,"-L7ip0Zis2igR_iNWBX_":0,"-L7ip12yyXn98laAuHd3":0,"-L7ip1YDa1ZeWwbfwoiT":0,"-L7ip21TAKZE5aYg6q2Z":0,"-L7ip2WimFYHAHkq10Jd":0,"-L7ip3-y8i4lo9ll6bY6":0,"-L7ip3VD6SOgrcfd3Y6h":0,"-L7ip3zTKEdqoDA3ajrf":0,"-L7ip4TiFwqPyO-ZXR16":0,"-L7ip4xyPBng6Sc8IdKJ":0,"-L7ip5SDH34HxBhfd-TB":0,"-L7ip5wTHLO3clt9qtqm":0,"-L7ip6Qhqsx5NXWrAn9Y":0,"-L7ip6uxr1X1lFe7Yk91":0,"-L7ip7PC0uU85f6zI4KB":0,"-L7ip7tSa0c0EY38z__Y":0,"-L7ip8NhIVZAK71DMO3A":0,"-L7ip8rxTllpDH2glvPG":0,"-L7ip9MCHJQfF2bC72aZ":0,"-L7ip9qSfPcGuIEIDVE4":0,"-L7ipAKhr0P3F6il1Lxr":0,"-L7ipAoxI13UmA5uP5z0":0,"-L7ipBJCTlEu6LB-hpjy":0,"-L7ipBnSxQUoZBVBye53":0,"-L7ipCHhKX3gzHs9QOjg":0,"-L7ipClxFTO597kC5zae":0,"-L7ipDGC2SiD--zQxjW9":0,"-L7ipDkSxvhDrjC5kiau":0,"-L7ipEEg1wac87097ZXu":0,"-L7ipEiwUvyOyVTrNAjG":0,"-L7ipFDBwlLmYhAEKltp":0,"-L7ipFhRFOz2G1DHgXXK":0,"-L7ipGBga7uVnG5NEPJF":0,"-L7ipGfw1Uc8YnRosyaN":0,"-L7ipHAC9qpEhF_Rgdg_":0,"-L7ipHeRq9zRAOteG9u0":0,"-L7ipI8gaLIemg632srm":0,"-L7ipIcw2O9mBdSKFoYr":0,"-L7ipJ7B7m1PSYUN5ept":0,"-L7ipJbR6g14TlLoznMi":0,"-L7ipK5gjuTBtgpd7hG9":0,"-L7ipL9qM-D2szaQqaSA":0,"-L7ipLZZhJFh97chxLcH":0,"-L7ipM2pAzqNBHIHZEur":0,"-L7ipMY566YosRU8uLRt":0,"-L7ipN1KwzCycdSjxFYh":0,"-L7ipNW_6NOVddngzhqM":0,"-L7ipO-ok4c2J9Ucx5yn":0,"-L7ipOV4p7Cv4J4wfcDL":0,"-L7ipOzJmXSKazLAUAiQ":0,"-L7ipPTZYrTPbgWuhaSc":0,"-L7ipPxo0SRm5sUYj5CG":0,"-L7ipQS3tDdtTwCJxUfD":0,"-L7ipQwJ7C3p0XD4PSLE":0,"-L7ipRQZK5M95rXvuCdq":0,"-L7ipRup6sIC9DfMg737":0,"-L7ipSP35C6uNUJLXJaY":0,"-L7ipStJrfGWA1_9CJNE":0,"-L7ipTNZqEZT2yUVZ-FY":0,"-L7ipTroK8YRcEbDzgNd":0,"-L7ipUM3EfxvPMA4LjaU":0,"-L7ipUqJfVwow8gnTQg4":0,"-L7ipVKZUZoaJW4ucQ0Q":0,"-L7ipVoo_baw0B4_Tw5K":0,"-L7ipWJ3wzaO9FrAPhV_":0,"-L7ipWnJRc7hX8DQZT54":0,"-L7ipXHY8-Mrp0jPS5l-":0,"-L7ipXlnVcGuzv-3MoqQ":0,"-L7ipYG2Qtgkht_MtI1D":0,"-L7ipYkIhzjvd2RcywUx":0,"-L7ipZEYkIyvhcQls2yn":0,"-L7ipZinlvjRuIJd363h":0,"-L7ip_D2oUT0wNOS6Uvz":0,"-L7ip_hImDGlS7SGQiVQ":0,"-L7ipaBYPVllaqcYiUp5":0,"-L7ipafnyuVkFuuqTPsH":0,"-L7ipbA2UXaVGl8t07yW":0,"-L7ipbeIdhiG1QjXLlmU":0,"-L7ipc8XJjg9ow5TIZk8":0,"-L7ipccnQMlGzpwPALzO":0,"-L7ipd72keC7ZqF_KaA-":0,"-L7ipdbH-Iw8UF5R8lmC":0,"-L7ipe5YuA3NitOnBdld":0,"-L7ipe_mGANk1-Q5l5TH":0,"-L7ipf41mw9roM4_PqK3":0,"-L7ipfZIkbE0-YjLBTOP":0,"-L7ipg2XLNW0NLlCmFJb":0,"-L7ipgXmtR2RCWqWf4lm":0,"-L7iph11fa5IJnxVoEq4":0,"-L7iphWHxiV1-7Az_ClH":0,"-L7ipi-Xt8FvHKLT_L6D":0,"-L7ipiUmjFcNWhRATitu":0,"-L7ipiz15DH_HyKOW1ig":0,"-L7ipjTH0zO34rUs80u_":0,"-L7ipjxXSsevZEBEWuT5":0,"-L7ipkRmnn7QntnhnQn5":0,"-L7ipkw1DAU8SxDQYwEk":0,"-L7iplQHETaYxF60EQf4":0,"-L7ipluXNHQ5CEN6NCC8":0,"-L7ipmOmOqyck4xONGnH":0,"-L7ipmt0jSMrGoooc3iR":0,"-L7ipnNH8K7fj7m3YYFr":0,"-L7ipnrWxAxpltPaMJ3B":0,"-L7ipoLmgOxEOKmZobco":0,"-L7ipoq0XxOXjdcdLj9i":0,"-L7ippKGrE2G54sqVsUL":0,"-L7ippoWNyJ2UbSK6QFl":0,"-L7ipqIlpKPl7LqQsmGt":0,"-L7ipqn0baDh7MKHcHm-":0,"-L7iprHGhTEKw6OmmBDa":0,"-L7iprlWIVKwIL3p3Lhz":0,"-L7ipsFlvuJqnFBMEJ4K":0,"-L7ipsk-JRsQmKGUav64":0,"-L7iptEGqb-oYOVA3uGp":0,"-L7iptiW0LhAfi3m8naD":0,"-L7ipuCljWrlB3uQC5bd":0,"-L7ipuh0yvIPDvs7wcES":0,"-L7ipvBFaycPkkKtzNWS":0,"-L7ipvfWdIdLUYdHOFdJ":0,"-L7ipw9ketvFKrBpalzt":0,"-L7ipwe-vMPFS16I95V0":0,"-L7ipx8FXKg31I_op_Xl":0,"-L7ipxcX9HDQfSW_xGRd":0,"-L7ipy6kwRhW-vsRtmb_":0,"-L7ipyb-6OUkZGUJ206H":0,"-L7ipz5F7r8Q1pvbmroV":0,"-L7ipz_V-ibUuCfoFvkE":0,"-L7iq-3k8rlbYD-rb_Yu":0,"-L7iq-Z-kGIbjmI1YMKu":0,"-L7iq02EVEFuz5ahcfR3":0,"-L7iq0XVBvPmjBrBrkOw":0,"-L7iq10kW5H8yeHB9ehf":0,"-L7iq1W-R8uRRq5Cve3N":0,"-L7iq2-FFWcKqeRYveft":0,"-L7iq2UVXs3vdvHBzh5G":0,"-L7iq2ykSXqsqgzZD3FV":0,"-L7iq3T-lSfBg2SwHIr2":0,"-L7iq3xEf2LQl38s3wPn":0,"-L7iq4RUcMlae6S4nUb2":0,"-L7iq4vjmdrq1wGF224V":0,"-L7iq5PzeZOpPHfnAQNT":0,"-L7iq5uEpjQ32AWiP59C":0,"-L7iq6OUEBhJRB_ilRnV":0,"-L7iq6sjf809DiFQ8DIj":0,"-L7iq7MzXa9COeNKRLXR":0,"-L7iqWkwLRF8zu5UNQRw":0,"-L7iqXFB9S27iFipl6Ba":0,"-L7iqXjRAFpklryNxnoB":0,"-L7iqYDgLuxzjj0-3D3H":0,"-L7iqYhwWCQJ95qiXSXv":0,"-L7iqZCB1qMS9Eoy9NAh":0,"-L7iqZgRZb5KEvr3kIb-":0,"-L7iq_AgZNUHKZUH2FbL":0,"-L7iq_ew5KKZ0hrvf0Ib":0,"-L7iqa9BN3AJL8ZNPISh":0,"-L7iqadRrHnEyuoISciw":0,"-L7iqb7gVWhCyFi4S66t":0,"-L7iqbbws74tTv_3GWia":0,"-L7iqc6BL7W1-JObFwqq":0,"-L7iqcaReT1ZiMjlIxQ1":0,"-L7iqd4f2Ogv75qGosw3":0,"-L7iqdZvRY_NPHZ_8R4X":0,"-L7iqe3903sRMSSgNu6R":0,"-L7iqeYQ2rTFximfVOdg":0,"-L7iqf1f03oyQVCiiJUf":0,"-L7iqfWvAQJuL4nNm93i":0,"-L7iqg0AF4H1T90Y_7FT":0,"-L7iqgVQDYkSogZm-xv7":0,"-L7iqgzfnwP6vkdJgojR":0,"-L7iqhTvdWbEqUBS0_0U":0,"-L7iqhyAcmJz8mvdDwdc":0,"-L7iqiSQ6ZIx9H6OWH8n":0,"-L7iqiwfFrEy_ThnUnza":0,"-L7iqjQvgxSxj4sctc6R":0,"-L7iqjv9NV8ZLmvvtFr_":0,"-L7iqkPQ4XDp3VMyGxjG":0,"-L7iqktepjebNsjNQXTI":0,"-L7iqlNu74z0KdJG2XFf":0,"-L7iqls9N4WcccOEDu4C":0,"-L7iqmMPPwcrLeygqckA":0,"-L7iqmqe26EOq6yZ4iEP":0,"-L7iqnKuNkZxPIkVtLLA":0,"-L7iqnp9vjZRrGH0Zxza":0,"-L7iqoJP5bN2UXfgdSwn":0,"-L7iqoneRj8yRdSuppWr":0,"-L7iqpHu7wwbO852M3Qh":0,"-L7iqpm9NAMOvP5EvrI0":0,"-L7iqqGPtPq8ZUS53CJV":0,"-L7iqqkevefonBfIh7NP":0,"-L7iqrEutYN9_tvInqco":0,"-L7iqrj9VwXf1i0rPErD":0,"-L7iqsDO3vKWq1ZIByIl":0,"-L7iqshdVTf1VjaEQ13u":0,"-L7iqtBtUv6_OIz1yNyG":0,"-L7iqtg8oneUgL29WMki":0,"-L7iquAOSHJvLEYGYqHA":0,"-L7iquedV0RpgcHagumI":0,"-L7iqv8ulqtxwt0a2J3n":0,"-L7iqvd7Iuk_2sD4jgXH":0,"-L7iqw7OqG_6E8A6QWQ0":0,"-L7iqwbd2VNgzAT7aTdz":0,"-L7iqx5tqRUbgXVKM1v0":0,"-L7iqxa8KI80-dCDWPOa":0,"-L7iqy4OO2fFAQNYKF12":0,"-L7iqyZdW8dAyU8yjYAv":0,"-L7iqz2t13e8BFWCr0Ro":0,"-L7iqzY84DMCSPGjPFVw":0,"-L7ir-1O-B0rbt29s8Sj":0,"-L7ir-WdOcbDEka8-ghd":0,"-L7ir0-s0GAUthl42PZ8":0,"-L7ir0V7K7Qd3z5BG3ij":0,"-L7ir0zNJlgtWAxbITMO":0,"-L7ir1TcoGJzUTuS0UZb":0,"-L7ir1xsx6yQhAOAY15x":0,"-L7ir2S7Z1JxYut4AoJw":0,"-L7ir2wN5nfo6Dkx5b4S":0,"-L7ir3QcYpiS6psH9rIF":0,"-L7ir3uryOUs_e9iQOdr":0,"-L7ir4P7l6piKWbgW_nk":0,"-L7ir4tNalV36wyu6l-e":0,"-L7ir5NcrMkXP2poX232":0,"-L7ir5rsGQzb1N40t5IJ":0,"-L7ir6M7T9YYmj7UE877":0,"-L7ir6qNy0T9ojwBzPUo":0,"-L7ir7KbIYMJFxAzQdyY":0,"-L7ir7osOAn6DAJpLObp":0,"-L7ir8J7pfBPIUQbRenA":0,"-L7ir8nMymBtp9oxISFU":0,"-L7ir9Hb1-PStaeIHA0V":0,"-L7ir9lreKUe8K_lu0Fu":0,"-L7irAG6X7dfLyv3dLDk":0,"-L7irAkMwmuwqzSEBjeE":0,"-L7irBEbe7w4I3rPLedV":0,"-L7irBisEpFTSzurbweA":0,"-L7irCD6Fz9drNybRTNL":0,"-L7irChMtU66BaRkCgC9":0,"-L7irDBbFssu6l9OW_1x":0,"-L7irDfrldd3cZT_ysS6":0,"-L7irEA6G4KTyBMSFwlq":0,"-L7irEeMXePiZDgmbnw0":0,"-L7irF8b-G6bNoC9tfBS":0,"-L7irFcrenR_kda3_gbj":0,"-L7irG76f86Li8Klwqhy":0,"-L7irGbMWQLm3soDFBHS":0,"-L7irH5b4uAzVgxQR2go":0,"-L7irH_rOrMZum59PzPt":0,"-L7irI46txA7KS2jDrpb":0,"-L7irIZLtEpudsTJzHBD":0,"-L7irJ2ag_X9GqEA77dI":0,"-L7irJXjISrW4NJbq80i":0,"-L7irK0z9uqbEMHT_bDb":0,"-L7irKWFOjf3OD68tokb":0,"-L7irL-Uq6NADBfdoe-s":0,"-L7irLUjHCCOdjiyFXFQ":0,"-L7irLyz5as9DsywxWqL":0,"-L7irMTDkAhpQU9zv0ME":0,"-L7irMxTIY2nkjabLOb_":0,"-L7irNRiTf0KXmfLQe8t":0,"-L7irNvyv7VV8pxAVm7u":0,"-L7irOQD7pcxP7SuvGmr":0,"-L7irOuT6FJmqqfia5WD":0,"-L7irPOiM7EHddJ3o1Q-":0,"-L7irPsyrY6oPr5ouzIW":0,"-L7irQNDQwz2-B2Y47GJ":0,"-L7irQrTnZfeyfJ9L5HW":0,"-L7irRLiOqI_mAFR5Sdb":0,"-L7irRpyxz0AOgkVxVsg":0,"-L7irSKDb0Iu0aJghNQY":0,"-L7irSoTFioiNIj6r_JL":0,"-L7irTIiv68jN_jpm8xg":0,"-L7irTmyPNloQPZiJe4B":0,"-L7irUHDPK-M5l70qSh7":0,"-L7irUlTJINsqVss4sDb":0,"-L7irVFibSY__aeWr9Rr":0,"-L7irVjxjgE7c0cAYyr7":0,"-L7irWEDYd1twiwMA51w":0,"-L7irWiSDN7B6SpAzOuf":0,"-L7irXChuwrCVZ2c9Zud":0,"-L7irXgxHeRkdYNUx60P":0,"-L7irYBC375B5tpE-l7c":0,"-L7irYfSG6G1IUklGkme":0,"-L7irZ9gTuVDh_Hqa8xa":0,"-L7irZdx7rDi_Ag3KOU2":0,"-L7ir_8C8L5mu7KJl78q":0,"-L7ir_cSAqJuPMc-D9go":0,"-L7ira6h0banPmNKpz76":0,"-L7iraaxidqdI0cbnOpg":0,"-L7irb5CKjziDkLSgcY7":0,"-L7irb_Stse16uwR-4ex":0,"-L7irc3hOLIQQcxqpcKM":0,"-L7ircYx8k3R1XJ_L4sp":0,"-L7ird2CbNBhUgfotGXk":0,"-L7irdXREioHiXtmnV6M":0,"-L7ire0gwsJNFioBE3u-":0,"-L7ireVwGjgv0t16Bdki":0,"-L7irf-BbWKQsa4MFOqH":0,"-L7irfURgMetPcQ-vBmi":0,"-L7irfyg_9-3OA1n3j29":0,"-L7irgSwbWFCWWTFmels":0,"-L7irgxBVdHl-hSoP8zc":0,"-L7irhRQ0dGbCemI_Xt5":0,"-L7irhvgROFTuiPJOalB":0,"-L7iriPwry6DAdwBmhf1":0,"-L7iriuBzUFqhm-_FgVm":0,"-L7irjORhaQF3KT_SMd3":0,"-L7irjsgfitYn1K45op5":0,"-L7irkMwg3ugvEOo9wpt":0,"-L7irkrBE_vdpRiWBa5-":0,"-L7irlLRguBRSxVh84Jo":0,"-L7irlpfsiP7P-8_18x1":0,"-L7irmJvk28ANEof8r8W":0,"-L7irmoA2p4sRU-dNhcu":0,"-L7irnIQk9zKB6LAXpS4":0,"-L7irnmfu59Y419mvN1r":0,"-L7iroGvzclBVeLsIOMr":0,"-L7irolAz17YaUPCYTah":0,"-L7irpFQqQtWJszzmpff":0,"-L7irpjf53f0II2GwyzF":0,"-L7irqDve8xYwVGY6oAa":0,"-L7irqiAepuLiXaXhjB_":0,"-L7irrCQ9VVDhAohEMu7":0,"-L7irrgf9cMrHIJCIFV_":0,"-L7irsAvbGRWthKeyHvS":0,"-L7irsfAssrffnaN4a1b":0,"-L7irt9QV-7sbUYosaFk":0,"-L7irtdfLDQvpCnSueez":0,"-L7iru7vaeDJHKvdJQex":0,"-L7iruc9IOv1JxVdaAem":0,"-L7irv6Qu_lqNnEWkfH0":0,"-L7irvaezc_ZTcNoiUDW":0,"-L7irw4uRk2rSYPHvFVs":0,"-L7irw_9MxH1cLunHux4":0,"-L7irx3PKHcaI5FBmFEm":0,"-L7irxYe7Uy3ON_WXO2-":0,"-L7iry1uQDKPhjE195-4":0,"-L7iryX9lN6LXLciCQO3":0,"-L7irz0PflTfDS5OeSTS":0,"-L7irzVeRr8vY8NM7is5":0,"-L7irzzu74PKgLkePpaW":0,"-L7is-U9Yd3AIeNkiSb5":0,"-L7is-yPo1wl5BhjKth8":0,"-L7is0Sd9KBJfeFDZKU0":0,"-L7is0wuPXiyBoVvs7Ls":0,"-L7is1R9AX736f2ZQuBU":0,"-L7is1vOiIiy8QqbyX0H":0,"-L7is2PetH4UXIWq17R5":0,"-L7is2ttOODt1hh8e3Z5":0,"-L7is3O8DsBjg6qOX7DO":0,"-L7is3sOC3Y7L7hS5h94":0,"-L7is4Md4EB952HX7beU":0,"-L7is4qtAA5j1GXzphgt":0,"-L7is5L8gvW2V8D86_o5":0,"-L7is5pOz5UCfSKoTT6Z":0,"-L7is6Jd_r9Nby0OWRbP":0,"-L7is6nt18g7L47e4dwq":0,"-L7is7I8PMFCaLukcU2q":0,"-L7is7mO7tbjzZZpgpQI":0,"-L7is8Gdfb0WYLWiOIrV":0,"-L7is8kt5Q4MPioXmQVd":0,"-L7is9F7ACuX7-sCjrcN":0,"-L7is9jOvbIMSEm3WIE3":0,"-L7isADdtlHjkbVdoKQq":0,"-L7isAhsRxy3ZjJ_1Bbz":0,"-L7isBC7jpQAZxqpzIeU":0,"-L7isBgN-CDazvNaRKpt":0,"-L7isCAcb4Dhlgqp90la":0,"-L7isCesSk-etTBNy_Po":0,"-L7isD9794ocL6_FddAI":0,"-L7isDdNTpHu01lHNK23":0,"-L7isE7cNEe2fPduY0j0":0,"-L7isEbsfQVub5Shd9MW":0,"-L7isF68qlxVTR4uRhM3":0,"-L7isFaN6awk_zq3bem_":0,"-L7isG4czqIg6_E8Qlf7":0,"-L7isGZsk_CAL4yhFx8r":0,"-L7isH37he7GjiheYlXz":0,"-L7isHYNpnUezugMNrBG":0,"-L7isI1cZ-aLEndVFdnY":0,"-L7isIWsqXdQQp2M8nP9":0,"-L7isJ06CAAKbY7_kzR9":0,"-L7isJVMa8PGDULZQk6Z":0,"-L7isJzbxVZSZNx9ewzZ":0,"-L7isKTrVIJpAHtvYj-a":0,"-L7isKy6-UtVF8mVQ7g7":0,"-L7isLSMfb5BAqO9jJBB":0,"-L7isLwbqa_w1iGMJi3S":0,"-L7isMQrg92ibnzX3cf1":0,"-L7isMv6KLhX9D2BQ2ue":0,"-L7isNPMfoySI_PxJtbH":0,"-L7isNtbRghEPH8bVtsS":0,"-L7isONrajFI8cH6FIwn":0,"-L7isOs6ZFP86THkJJVu":0,"-L7isPMMTsCIdpgTV9PI":0,"-L7isPqbgd3D2XexLWnm":0,"-L7isQKqLG7rYd-fnzzU":0,"-L7isQp5-NWYmXtYpb6j":0,"-L7isRJMBiDzhMPqTM0q":0,"-L7isRnafjuLomTcMcpV":0,"-L7isSHrxyfYKfNugKs2":0,"-L7isSm5-hbqEgcXZqqM":0,"-L7isTGLoW9W4OVHJ8bU":0,"-L7isTka67BhWPY5oMti":0,"-L7isUEqJmL7_DDCPFQz":0,"-L7isUj57tqC7pRzLa9Z":0,"-L7isVDLPzAkVv7IwknL":0,"-L7isVhaJe7P4SD_LQme":0,"-L7isWBqBSWmEs9wig7E":0,"-L7isWg5FqaoIa32Fyi8":0,"-L7isXAL4LzMjXWa5h5t":0,"-L7isXeawFcYMR2_n8v9":0,"-L7isY8qj3FtoUtDCOvT":0,"-L7isYd5est4dk32W7_G":0,"-L7isZ7LkZkcFCp-oMc9":0,"-L7isZbarsO_iy17wbf4":0,"-L7is_5pAXbAk35e107J":0,"-L7is_a5fI0SKKCuNCJU":0,"-L7isa4LBi_AE002QqKC":0,"-L7isaZal9HrCs1ibzHJ":0,"-L7isb2p7rYHTHw2t8z5":0,"-L7isbY477T4dB_ZlrDr":0,"-L7isc1KidUmQHiYhXLq":0,"-L7iscW_-WyEONx8veD6":0,"-L7isd-pCmr89418sib0":0,"-L7isdV4-_YIJGD5VF17":0,"-L7isdzKHzJvS0516dOE":0,"-L7iseT_wwJpPMAmziGW":0,"-L7isexpe7SG56EpO-Kg":0,"-L7isfS4dNFtwZ2JwEMH":0,"-L7isfwJ6rjEsRl2Ty3b":0,"-L7isgQ_tk7ZV9V48cWd":0,"-L7isgup_PkA6s45Upys":0,"-L7ishP4ysinJt53o7An":0,"-L7ishtK7ObG8_TeDg9Z":0,"-L7isiN_DlUjGu2VVc6g":0,"-L7isirofjd-zZbAbEUw":0,"-L7isjM39RVJqZvc-EmX":0,"-L7isjqJWt3vYTilRO8p":0,"-L7iskKZw5Rj3RnEWE4b":0,"-L7iskooA5cInqElHQac":0,"-L7islJ3sBB_Osd93fVk":0,"-L7islnJmCvDHfx07uWF":0,"-L7ismHZ0JnuItWB6_-L":0,"-L7ismloTXKZbe2rhHER":0,"-L7isnG3Z-J8mlCT6z-G":0,"-L7isnkJ3-HzD93XzD3E":0,"-L7isoEZpiPuWzx1-pwe":0,"-L7isoio755tawIgv2d2":0,"-L7ispD3MHfWR8JvL9Rm":0,"-L7isphJ5db-wR5PxFrr":0,"-L7isqBZJUvI4UuiK59l":0,"-L7isqfoJa0JJcg9c1IY":0,"-L7isrA2I2mdmsfM3074":0,"-L7isreIcEeQklc24qZK":0,"-L7iss8Ytqm3zKZaXZfg":0,"-L7isscnLBiVtF9pTEcv":0,"-L7ist72XzowQ9E50fN4":0,"-L7istbIQzKiKpc_IoiM":0,"-L7isu5YdhiFQsow8HqS":0,"-L7isu_nWSjCwT-7Gm4l":0,"-L7isv429n86kgMbvQ_I":0,"-L7isvZIuCoY-edFp9G4":0,"-L7isw2Ye8ezxTZ62XFY":0,"-L7iswXn8G8rnsJgduQL":0,"-L7isx12gEelZ-AIoJlv":0,"-L7isxWIGul9TRPZBC4q":0,"-L7isy-YwX6G8N-0c0-w":0,"-L7isyUnvG4I4eIxwq8c":0,"-L7isyz2fH8CQ2bJVtju":0,"-L7iszTIryAijlKNW1L-":0,"-L7iszxY4PyoTl2s6X_R":0,"-L7it-Rm6U4ZnE6eZvWh":0,"-L7it-w2rbrAyID0XElp":0,"-L7it0QHjV9EnE2Kf2kW":0,"-L7it0uXMMHU_5A_kJBZ":0,"-L7it1Om5oT4qjR5MfYN":0,"-L7it1t1d4PWxtmtAqDc":0,"-L7it2NHG-O79umBUiUm":0,"-L7it2rXB4ZZB4GgLdHO":0,"-L7it3Lm4udjwsN_owm7":0,"-L7it3q1DbBzpS383L57":0,"-L7it4KHuKcnh4c7rpzu":0,"-L7it4oXGDAKBUEasSTC":0,"-L7it5ImrS3Noj1yEdHf":0,"-L7it5n1jRJ9HTwz2Xho":0,"-L7it6HH60m-a12230fg":0,"-L7it6lXFDPmcGIkM_xx":0,"-L7it7Fluh-iDrcj-TmB":0,"-L7it7k1314BEV-s0emP":0,"-L7it8EGk8BO7uwuNo74":0,"-L7it8iWKIswpoQPUIA9":0,"-L7it9ClKF5rXb61xBYI":0,"-L7it9h0_owsT-2eMoRg":0,"-L7itABG7IQS4eWNhjf-":0,"-L7itAfWi9ih0G2TsiuY":0,"-L7itB9kTs8HPHkAwNMi":0,"-L7itBe0jhosZeANMuih":0,"-L7itC8F0N_d9Wech36y":0,"-L7itCcWznNJ5ZrKEuWk":0,"-L7itD6l99XaL3DeKgKi":0}